{"version":2,"kind":"Article","sha256":"c13760bd15540e5774e02ff4327ba931bebad637d855d1db37b074b52f854593","slug":"notebooks.set-up-earthdata-login","location":"/notebooks/set_up_Earthdata_Login.md","dependencies":[],"frontmatter":{"title":"Set Up an Earthdata Login Account for NISAR Data Access","content_includes_title":false,"authors":[{"nameParsed":{"literal":"The Alaska Satellite Facility","given":"The Alaska Satellite","family":"Facility"},"name":"The Alaska Satellite Facility","id":"contributors-myst-generated-uid-0"}],"open_access":true,"license":{"content":{"id":"BSD-3-Clause","url":"https://opensource.org/licenses/BSD-3-Clause","name":"BSD 3-Clause \"New\" or \"Revised\" License","free":true,"osi":true}},"github":"https://github.com/ASFOpenSARlab/NISAR_GCOV_Cookbook","copyright":"2025","affiliations":[{"id":"UAF","name":"University of Alaska Fairbanks","department":"Geophysical Institute","url":"https://www.gi.alaska.edu/"},{"id":"ASF","name":"Alaska Satellite Facility","url":"https://asf.alaska.edu/"}],"numbering":{"title":{"offset":1}},"source_url":"https://github.com/ASFOpenSARlab/NISAR_GCOV_Cookbook/blob/main/notebooks/set_up_Earthdata_Login.md","edit_url":"https://github.com/ASFOpenSARlab/NISAR_GCOV_Cookbook/edit/main/notebooks/set_up_Earthdata_Login.md","thumbnail":"/NISAR_GCOV_Cookbook/build/EDL_landing_page-7f04fe7fa7d48ac66b4c0a66d2f67a09.png","exports":[{"format":"md","filename":"set_up_Earthdata_Login.md","url":"/NISAR_GCOV_Cookbook/build/set_up_Earthdata_Log-5b03a8ab963c4f80836a45deec250d42.md"}]},"mdast":{"type":"root","children":[{"type":"block","children":[{"type":"break","key":"ojLtvDsdwT"},{"type":"paragraph","position":{"start":{"line":5,"column":1},"end":{"line":5,"column":1}},"children":[{"type":"text","value":"You must have an Earthdata Login account and accept the ","position":{"start":{"line":5,"column":1},"end":{"line":5,"column":1}},"key":"pvBaaadflI"},{"type":"inlineCode","value":"Alaska Satellite Facility Data Access","position":{"start":{"line":5,"column":1},"end":{"line":5,"column":1}},"key":"LkpU9gXH1R"},{"type":"text","value":" ","position":{"start":{"line":5,"column":1},"end":{"line":5,"column":1}},"key":"SWi7l4nxRI"},{"type":"abbreviation","title":"End User License Agreement","children":[{"type":"text","value":"EULA","key":"jfm9qwElss"}],"key":"ifGKD57LPG"},{"type":"text","value":" to access NISAR data.","position":{"start":{"line":5,"column":1},"end":{"line":5,"column":1}},"key":"puZBj79LTg"}],"key":"v1Ak8N8B6C"},{"type":"heading","depth":2,"position":{"start":{"line":7,"column":1},"end":{"line":7,"column":1}},"children":[{"type":"text","value":"Create an Earthdata Login Account","position":{"start":{"line":7,"column":1},"end":{"line":7,"column":1}},"key":"keYMcEFMdS"}],"identifier":"create-an-earthdata-login-account","label":"Create an Earthdata Login Account","html_id":"create-an-earthdata-login-account","implicit":true,"key":"NjOPr9mTz4"},{"type":"list","ordered":true,"start":1,"spread":false,"position":{"start":{"line":9,"column":1},"end":{"line":11,"column":1}},"children":[{"type":"listItem","spread":true,"position":{"start":{"line":9,"column":1},"end":{"line":9,"column":1}},"children":[{"type":"paragraph","children":[{"type":"text","value":"Navigate to Earthdata Login: ","position":{"start":{"line":9,"column":1},"end":{"line":9,"column":1}},"key":"YpZmLDyCee"},{"type":"link","url":"https://urs.earthdata.nasa.gov/","position":{"start":{"line":9,"column":1},"end":{"line":9,"column":1}},"children":[{"type":"text","value":"https://​urs​.earthdata​.nasa​.gov/","position":{"start":{"line":9,"column":1},"end":{"line":9,"column":1}},"key":"CImQyPtmkX"}],"urlSource":"https://urs.earthdata.nasa.gov/","key":"Kv5qiYuKzF"}],"key":"jNYr6sq9ze"}],"key":"WkgOTDfJWK"},{"type":"listItem","spread":true,"position":{"start":{"line":10,"column":1},"end":{"line":11,"column":1}},"children":[{"type":"paragraph","children":[{"type":"text","value":"Click the ","position":{"start":{"line":10,"column":1},"end":{"line":10,"column":1}},"key":"lo4ySXFTwE"},{"type":"inlineCode","value":"REGISTER FOR A PROFILE","position":{"start":{"line":10,"column":1},"end":{"line":10,"column":1}},"key":"eVAhVLORWm"},{"type":"text","value":" button.","position":{"start":{"line":10,"column":1},"end":{"line":10,"column":1}},"key":"FTjbwKWg1H"}],"key":"PEE24H6L0L"}],"key":"hFGC71Qui3"}],"key":"pw0lH2QsKy"},{"type":"container","kind":"figure","children":[{"type":"image","url":"/NISAR_GCOV_Cookbook/build/EDL_landing_page-7f04fe7fa7d48ac66b4c0a66d2f67a09.png","alt":"Image of the Earthdata Login landing page","key":"WdzRCTZZ0v","urlSource":"../assets/EDL_landing_page.png"}],"enumerator":"1","key":"UIx87Clkd2"},{"type":"list","ordered":true,"start":3,"spread":false,"position":{"start":{"line":17,"column":1},"end":{"line":20,"column":1}},"children":[{"type":"listItem","spread":true,"position":{"start":{"line":17,"column":1},"end":{"line":17,"column":1}},"children":[{"type":"paragraph","children":[{"type":"text","value":"Complete the registration form to create an account.","position":{"start":{"line":17,"column":1},"end":{"line":17,"column":1}},"key":"xDdaDzdiwH"}],"key":"STBYwRSQVm"}],"key":"W2BlCaGaVG"},{"type":"listItem","spread":true,"position":{"start":{"line":18,"column":1},"end":{"line":18,"column":1}},"children":[{"type":"paragraph","children":[{"type":"text","value":"Click the emailed link to verify your email address.","position":{"start":{"line":18,"column":1},"end":{"line":18,"column":1}},"key":"avizgAOehx"}],"key":"ouVPnORm6R"}],"key":"Le1leiUhwo"},{"type":"listItem","spread":true,"position":{"start":{"line":19,"column":1},"end":{"line":20,"column":1}},"children":[{"type":"paragraph","children":[{"type":"text","value":"Log into your new Earthdata Login account","position":{"start":{"line":19,"column":1},"end":{"line":19,"column":1}},"key":"Wh7DqjQeUr"}],"key":"d2L6aY4a8Q"}],"key":"SEx1dhnKZC"}],"key":"Lf1Htw6UQH"},{"type":"heading","depth":2,"position":{"start":{"line":21,"column":1},"end":{"line":21,"column":1}},"children":[{"type":"text","value":"Accept the ","position":{"start":{"line":21,"column":1},"end":{"line":21,"column":1}},"key":"ggCzdu1uhC"},{"type":"inlineCode","value":"Alaska Satellite Facility Data Access","position":{"start":{"line":21,"column":1},"end":{"line":21,"column":1}},"key":"KGyOeazUfo"},{"type":"text","value":" ","position":{"start":{"line":21,"column":1},"end":{"line":21,"column":1}},"key":"yMl1MoMo5p"},{"type":"abbreviation","title":"End User License Agreement","children":[{"type":"text","value":"EULA","key":"Z7BjfeBekF"}],"key":"LhubbUBYQL"}],"identifier":"accept-the-alaska-satellite-facility-data-access-eula","label":"Accept the Alaska Satellite Facility Data Access EULA","html_id":"accept-the-alaska-satellite-facility-data-access-eula","implicit":true,"key":"pva32zrwDA"},{"type":"list","ordered":true,"start":1,"spread":false,"position":{"start":{"line":23,"column":1},"end":{"line":25,"column":1}},"children":[{"type":"listItem","spread":true,"position":{"start":{"line":23,"column":1},"end":{"line":23,"column":1}},"children":[{"type":"paragraph","children":[{"type":"text","value":"Navigate to the ","position":{"start":{"line":23,"column":1},"end":{"line":23,"column":1}},"key":"VpqjtlnCJc"},{"type":"inlineCode","value":"EULAs","position":{"start":{"line":23,"column":1},"end":{"line":23,"column":1}},"key":"Hv5827r2Bb"},{"type":"text","value":" tab in your Earthdata Login account.","position":{"start":{"line":23,"column":1},"end":{"line":23,"column":1}},"key":"qrgRU9FNfG"}],"key":"t4DiO1OU93"}],"key":"lAMpADVX3l"},{"type":"listItem","spread":true,"position":{"start":{"line":24,"column":1},"end":{"line":25,"column":1}},"children":[{"type":"paragraph","children":[{"type":"text","value":"Click the ","position":{"start":{"line":24,"column":1},"end":{"line":24,"column":1}},"key":"ULfr0IqlG9"},{"type":"inlineCode","value":"Accept New EULAs","position":{"start":{"line":24,"column":1},"end":{"line":24,"column":1}},"key":"KdwknL8Ucx"},{"type":"text","value":" link.","position":{"start":{"line":24,"column":1},"end":{"line":24,"column":1}},"key":"Lhoe7Jhew2"}],"key":"gpc3ItzFj6"}],"key":"OB0fyjE0if"}],"key":"m0ELjqdNXb"},{"type":"container","kind":"figure","children":[{"type":"image","url":"/NISAR_GCOV_Cookbook/build/EDL_EULA_tab-9f367ca306b835ca83abe64b9b78b58d.png","alt":"Image showing the Earthdata Login Eula tab","key":"YslIX3AFfG","urlSource":"../assets/EDL_EULA_tab.png"}],"enumerator":"2","key":"G86TgCnwqE"},{"type":"list","ordered":true,"start":3,"spread":false,"position":{"start":{"line":31,"column":1},"end":{"line":32,"column":1}},"children":[{"type":"listItem","spread":true,"position":{"start":{"line":31,"column":1},"end":{"line":32,"column":1}},"children":[{"type":"paragraph","children":[{"type":"text","value":"Scroll to the bottom of the EULA list, find the ","position":{"start":{"line":31,"column":1},"end":{"line":31,"column":1}},"key":"dCsumD3Qay"},{"type":"inlineCode","value":"Alaska Satellite Facility Data Access","position":{"start":{"line":31,"column":1},"end":{"line":31,"column":1}},"key":"cqvaPMalSG"},{"type":"text","value":" entry and click its ","position":{"start":{"line":31,"column":1},"end":{"line":31,"column":1}},"key":"ScYNshwKie"},{"type":"inlineCode","value":"ACCEPT EULA","position":{"start":{"line":31,"column":1},"end":{"line":31,"column":1}},"key":"Hrl1JldJOd"},{"type":"text","value":" button.","position":{"start":{"line":31,"column":1},"end":{"line":31,"column":1}},"key":"HQFmDPoB8o"}],"key":"YJLkjXmCrz"}],"key":"PbIFMuNmEM"}],"key":"p1MscBjpOb"},{"type":"container","kind":"figure","children":[{"type":"image","url":"/NISAR_GCOV_Cookbook/build/EDL_ASF_EULA-cf3977ad1078d020671b42ac0fa3a53d.png","alt":"Image showing the \"Alaska Satellite Facility Data Access\" \"ACCEPT EULA\" button","key":"OXscXk9I4w","urlSource":"../assets/EDL_ASF_EULA.png"}],"enumerator":"3","key":"P4bAi1K0Pa"},{"type":"list","ordered":true,"start":4,"spread":false,"position":{"start":{"line":38,"column":1},"end":{"line":40,"column":1}},"children":[{"type":"listItem","spread":true,"position":{"start":{"line":38,"column":1},"end":{"line":38,"column":1}},"children":[{"type":"paragraph","children":[{"type":"text","value":"A EULA will appear. Read it and scroll to the bottom. Agree to the terms by clicking the checkbox.","position":{"start":{"line":38,"column":1},"end":{"line":38,"column":1}},"key":"L9KhHmzHlw"}],"key":"iUrKjRKzE7"}],"key":"T2WTHataIc"},{"type":"listItem","spread":true,"position":{"start":{"line":39,"column":1},"end":{"line":40,"column":1}},"children":[{"type":"paragraph","children":[{"type":"text","value":"Click the ","position":{"start":{"line":39,"column":1},"end":{"line":39,"column":1}},"key":"yMTRUwFzqG"},{"type":"inlineCode","value":"AGREE","position":{"start":{"line":39,"column":1},"end":{"line":39,"column":1}},"key":"w5VPpy3LRS"},{"type":"text","value":" button.","position":{"start":{"line":39,"column":1},"end":{"line":39,"column":1}},"key":"HW9z0NqQal"}],"key":"wE8iTkMHSo"}],"key":"crY0KmuNdw"}],"key":"kJlANYY6VM"},{"type":"container","kind":"figure","children":[{"type":"image","url":"/NISAR_GCOV_Cookbook/build/EDL_accept_EULA-9e46016fa7dbc793e463d672bef25921.png","alt":"","key":"vKz9xFLKGO","urlSource":"../assets/EDL_accept_EULA.png"}],"enumerator":"4","key":"B3TBvNvw8a"}],"key":"qKULYqMrZ5"}],"key":"vIbdshkP4X"},"references":{"cite":{"order":[],"data":{}}},"footer":{"navigation":{"prev":{"title":"Install Required Software Environment","url":"/notebooks/create-software-environment","group":"Prerequisites"},"next":{"title":"Explore an Example NISAR GCOV Backscatter Time Series","url":"/notebooks/nisar-gcov-time-series-example","group":"Placeholder (unorganized notebooks)"}}},"domain":"http://localhost:3000"}