{"version":3,"kind":"Notebook","sha256":"d12cea33385b58f83eb9ce1dece9918ae7319b8f2af924cff3839e6c85ee10fb","slug":"notebooks.opening-hdf5-python","location":"/notebooks/Opening_HDF5_Python.ipynb","dependencies":[],"frontmatter":{"title":"Opening NISAR GCOV HDF5 Files in Python","content_includes_title":false,"kernelspec":{"name":"isce3","display_name":"isce3 (Python)","language":"python"},"authors":[{"nameParsed":{"literal":"The Alaska Satellite Facility","given":"The Alaska Satellite","family":"Facility"},"name":"The Alaska Satellite Facility","id":"contributors-myst-generated-uid-0"}],"open_access":true,"license":{"content":{"id":"BSD-3-Clause","url":"https://opensource.org/licenses/BSD-3-Clause","name":"BSD 3-Clause \"New\" or \"Revised\" License","free":true,"osi":true}},"github":"https://github.com/ASFOpenSARlab/NISAR_GCOV_Cookbook","copyright":"2025","affiliations":[{"id":"UAF","name":"University of Alaska Fairbanks","department":"Geophysical Institute","url":"https://www.gi.alaska.edu/"},{"id":"ASF","name":"Alaska Satellite Facility","url":"https://asf.alaska.edu/"}],"numbering":{"title":{"offset":1}},"source_url":"https://github.com/ASFOpenSARlab/NISAR_GCOV_Cookbook/blob/main/notebooks/Opening_HDF5_Python.ipynb","edit_url":"https://github.com/ASFOpenSARlab/NISAR_GCOV_Cookbook/edit/main/notebooks/Opening_HDF5_Python.ipynb","exports":[{"format":"ipynb","filename":"Opening_HDF5_Python.ipynb","url":"/NISAR_GCOV_Cookbook/build/Opening_HDF5_Python-3cb267b0f83bbd6d951178fe7c53d0d4.ipynb"}]},"widgets":{},"mdast":{"type":"root","children":[{"type":"block","kind":"notebook-content","children":[{"type":"break","key":"WAxaIPgo3z"},{"type":"paragraph","position":{"start":{"line":5,"column":1},"end":{"line":5,"column":1}},"children":[{"type":"text","value":"This notebook demonstrates how to open and access NISAR GCOV HDF5 files using ","position":{"start":{"line":5,"column":1},"end":{"line":5,"column":1}},"key":"YJnUdlM3lm"},{"type":"inlineCode","value":"h5py","position":{"start":{"line":5,"column":1},"end":{"line":5,"column":1}},"key":"Q5aEjK7z5Y"},{"type":"text","value":" (Python), focusing on navigating GCOV files to locate and extract data of interest.","position":{"start":{"line":5,"column":1},"end":{"line":5,"column":1}},"key":"w0c2Hjdlhd"}],"key":"TjzirNZKHJ"},{"type":"paragraph","position":{"start":{"line":7,"column":1},"end":{"line":7,"column":1}},"children":[{"type":"text","value":"This notebook is intended for users with basic Python experience who want to work directly with NISAR GCOV products, including scientists, students, and practitioners transitioning from GeoTIFF-based SAR products to HDF5-based formats.","position":{"start":{"line":7,"column":1},"end":{"line":7,"column":1}},"key":"cytLd6TRn1"}],"key":"xf5ldxfKc8"},{"type":"thematicBreak","key":"dWsQrHazdm"},{"type":"heading","depth":2,"position":{"start":{"line":11,"column":1},"end":{"line":11,"column":1}},"children":[{"type":"text","value":"Overview","position":{"start":{"line":11,"column":1},"end":{"line":11,"column":1}},"key":"jGadHycQfv"}],"identifier":"overview","label":"Overview","html_id":"overview","implicit":true,"key":"kIzAbSxn9M"},{"type":"list","ordered":true,"start":1,"spread":false,"position":{"start":{"line":13,"column":1},"end":{"line":25,"column":1}},"children":[{"type":"listItem","spread":true,"position":{"start":{"line":13,"column":1},"end":{"line":13,"column":1}},"children":[{"type":"paragraph","children":[{"type":"crossReference","position":{"start":{"line":13,"column":1},"end":{"line":13,"column":1}},"children":[{"type":"text","value":"Prerequisites","position":{"start":{"line":13,"column":1},"end":{"line":13,"column":1}},"key":"Hb1B4RVSLz"}],"identifier":"hdf5-prereqs","label":"hdf5-prereqs","kind":"heading","template":"{name}","resolved":true,"html_id":"hdf5-prereqs","key":"WYbjvc5Nn3"}],"key":"fUN6etahrK"}],"key":"ukHQYzYjfd"},{"type":"listItem","spread":true,"position":{"start":{"line":14,"column":1},"end":{"line":14,"column":1}},"children":[{"type":"paragraph","children":[{"type":"crossReference","position":{"start":{"line":14,"column":1},"end":{"line":14,"column":1}},"children":[{"type":"text","value":"Download a NISAR GCOV HDF5 file","position":{"start":{"line":14,"column":1},"end":{"line":14,"column":1}},"key":"VkV5ih6vjz"}],"identifier":"hdf5-download","label":"hdf5-download","kind":"heading","template":"{name}","resolved":true,"html_id":"hdf5-download","key":"FPoZOV5gIH"}],"key":"Wxr63nxTn6"}],"key":"HoWjqobKT6"},{"type":"listItem","spread":true,"position":{"start":{"line":15,"column":1},"end":{"line":15,"column":1}},"children":[{"type":"paragraph","children":[{"type":"crossReference","position":{"start":{"line":15,"column":1},"end":{"line":15,"column":1}},"children":[{"type":"text","value":"Accessing the science group","position":{"start":{"line":15,"column":1},"end":{"line":15,"column":1}},"key":"GVSL5WUvtm"}],"identifier":"hdf5-science","label":"hdf5-science","kind":"heading","template":"{name}","resolved":true,"html_id":"hdf5-science","key":"zVJwB4MFm6"}],"key":"p6a2sMwOVJ"}],"key":"KESYPlB5w6"},{"type":"listItem","spread":true,"position":{"start":{"line":16,"column":1},"end":{"line":16,"column":1}},"children":[{"type":"paragraph","children":[{"type":"crossReference","position":{"start":{"line":16,"column":1},"end":{"line":16,"column":1}},"children":[{"type":"text","value":"Accessing the LSAR group","position":{"start":{"line":16,"column":1},"end":{"line":16,"column":1}},"key":"dnKedA2zSH"}],"identifier":"hdf5-lsar","label":"hdf5-lsar","kind":"heading","template":"{name}","resolved":true,"html_id":"hdf5-lsar","key":"jOTSriCmb1"}],"key":"vWJITqPEaG"}],"key":"gJ2A4YcwLA"},{"type":"listItem","spread":true,"position":{"start":{"line":17,"column":1},"end":{"line":17,"column":1}},"children":[{"type":"paragraph","children":[{"type":"crossReference","position":{"start":{"line":17,"column":1},"end":{"line":17,"column":1}},"children":[{"type":"text","value":"Accessing the GCOV group","position":{"start":{"line":17,"column":1},"end":{"line":17,"column":1}},"key":"vMnp5QLIVi"}],"identifier":"hdf5-gcov","label":"hdf5-gcov","kind":"heading","template":"{name}","resolved":true,"html_id":"hdf5-gcov","key":"RCsPdKpRYw"}],"key":"Zf2QqbY6a1"}],"key":"v6BmwYZArK"},{"type":"listItem","spread":true,"position":{"start":{"line":18,"column":1},"end":{"line":18,"column":1}},"children":[{"type":"paragraph","children":[{"type":"crossReference","position":{"start":{"line":18,"column":1},"end":{"line":18,"column":1}},"children":[{"type":"text","value":"Navigating into the grids group","position":{"start":{"line":18,"column":1},"end":{"line":18,"column":1}},"key":"vrDcxINSmV"}],"identifier":"hdf5-grids","label":"hdf5-grids","kind":"heading","template":"{name}","resolved":true,"html_id":"hdf5-grids","key":"bQAprJgaHL"}],"key":"Na3B5norNh"}],"key":"jDPzBhJDUH"},{"type":"listItem","spread":true,"position":{"start":{"line":19,"column":1},"end":{"line":19,"column":1}},"children":[{"type":"paragraph","children":[{"type":"crossReference","position":{"start":{"line":19,"column":1},"end":{"line":19,"column":1}},"children":[{"type":"text","value":"Inspecting datasets within a frequency group","position":{"start":{"line":19,"column":1},"end":{"line":19,"column":1}},"key":"m6nsqOaqup"}],"identifier":"hdf5-frequency","label":"hdf5-frequency","kind":"heading","template":"{name}","resolved":true,"html_id":"hdf5-frequency","key":"cZ212hNLUu"}],"key":"nWS4ZDh2NS"}],"key":"qABbfcErh2"},{"type":"listItem","spread":true,"position":{"start":{"line":20,"column":1},"end":{"line":20,"column":1}},"children":[{"type":"paragraph","children":[{"type":"crossReference","position":{"start":{"line":20,"column":1},"end":{"line":20,"column":1}},"children":[{"type":"text","value":"Accessing a specific GCOV dataset","position":{"start":{"line":20,"column":1},"end":{"line":20,"column":1}},"key":"L10sFShzlk"}],"identifier":"hdf5-gcov_dataset","label":"hdf5-gcov_dataset","kind":"heading","template":"{name}","resolved":true,"html_id":"hdf5-gcov-dataset","key":"uj0Z4BStI0"}],"key":"hzNzP2vJqE"}],"key":"PUnounTosJ"},{"type":"listItem","spread":true,"position":{"start":{"line":21,"column":1},"end":{"line":21,"column":1}},"children":[{"type":"paragraph","children":[{"type":"crossReference","position":{"start":{"line":21,"column":1},"end":{"line":21,"column":1}},"children":[{"type":"text","value":"Reading the dataset into memory","position":{"start":{"line":21,"column":1},"end":{"line":21,"column":1}},"key":"jlhKqoIxif"}],"identifier":"hdf5-readmemory","label":"hdf5-readmemory","kind":"heading","template":"{name}","resolved":true,"html_id":"hdf5-readmemory","key":"qoSiGA9r66"}],"key":"fbg014Z9Lv"}],"key":"XqOOYLIlrX"},{"type":"listItem","spread":true,"position":{"start":{"line":22,"column":1},"end":{"line":22,"column":1}},"children":[{"type":"paragraph","children":[{"type":"crossReference","position":{"start":{"line":22,"column":1},"end":{"line":22,"column":1}},"children":[{"type":"text","value":"Build a raster transform and export to GeoTIFF","position":{"start":{"line":22,"column":1},"end":{"line":22,"column":1}},"key":"yxnPXwFHnm"}],"identifier":"hdf5-geotiff","label":"hdf5-geotiff","kind":"heading","template":"{name}","resolved":true,"html_id":"hdf5-geotiff","key":"m6DgCzckEJ"}],"key":"lh1xrq6lcm"}],"key":"VgdQgypNsG"},{"type":"listItem","spread":true,"position":{"start":{"line":23,"column":1},"end":{"line":23,"column":1}},"children":[{"type":"paragraph","children":[{"type":"crossReference","position":{"start":{"line":23,"column":1},"end":{"line":23,"column":1}},"children":[{"type":"text","value":"Summary","position":{"start":{"line":23,"column":1},"end":{"line":23,"column":1}},"key":"PV2sqTeIYK"}],"identifier":"hdf5-summary","label":"hdf5-summary","kind":"heading","template":"{name}","resolved":true,"html_id":"hdf5-summary","key":"u2Cb0hSyjP"}],"key":"xNJDypnRU4"}],"key":"h99SNL1xEk"},{"type":"listItem","spread":true,"position":{"start":{"line":24,"column":1},"end":{"line":25,"column":1}},"children":[{"type":"paragraph","children":[{"type":"crossReference","position":{"start":{"line":24,"column":1},"end":{"line":24,"column":1}},"children":[{"type":"text","value":"Resources and References","position":{"start":{"line":24,"column":1},"end":{"line":24,"column":1}},"key":"qswmYDDX9N"}],"identifier":"hdf5-resources","label":"hdf5-resources","kind":"heading","template":"{name}","resolved":true,"html_id":"hdf5-resources","key":"UNDPbDs4Oq"}],"key":"bJTukg2gxA"}],"key":"nHwQpIVPhP"}],"key":"eUyMSyaW9s"},{"type":"thematicBreak","key":"TQykIFthJw"},{"type":"heading","depth":2,"position":{"start":{"line":29,"column":1},"end":{"line":29,"column":1}},"children":[{"type":"text","value":"1. Prerequisites","position":{"start":{"line":29,"column":1},"end":{"line":29,"column":1}},"key":"lGtR7yzkeT"}],"label":"hdf5-prereqs","identifier":"hdf5-prereqs","html_id":"hdf5-prereqs","key":"o2RWREb31e"},{"type":"table","position":{"start":{"line":30,"column":1},"end":{"line":32,"column":1}},"children":[{"type":"tableRow","position":{"start":{"line":30,"column":1},"end":{"line":30,"column":1}},"children":[{"type":"tableCell","header":true,"position":{"start":{"line":30,"column":1},"end":{"line":30,"column":1}},"children":[{"type":"text","value":"Prerequisite","position":{"start":{"line":30,"column":1},"end":{"line":30,"column":1}},"key":"uLy2600GZS"}],"key":"GJI0O8XAFB"},{"type":"tableCell","header":true,"position":{"start":{"line":30,"column":1},"end":{"line":30,"column":1}},"children":[{"type":"text","value":"Importance","position":{"start":{"line":30,"column":1},"end":{"line":30,"column":1}},"key":"Isv793EBE0"}],"key":"zg9xVSPplH"},{"type":"tableCell","header":true,"position":{"start":{"line":30,"column":1},"end":{"line":30,"column":1}},"children":[{"type":"text","value":"Notes","position":{"start":{"line":30,"column":1},"end":{"line":30,"column":1}},"key":"HxkxmRA8JR"}],"key":"Rklsqkjf0A"}],"key":"KpvNMhYABf"},{"type":"tableRow","position":{"start":{"line":32,"column":1},"end":{"line":32,"column":1}},"children":[{"type":"tableCell","position":{"start":{"line":32,"column":1},"end":{"line":32,"column":1}},"children":[{"type":"link","url":"https://github.com/ASFOpenSARlab/NISAR_GCOV_Cookbook/blob/main/notebooks/software_environment_docker.ipynb","position":{"start":{"line":32,"column":1},"end":{"line":32,"column":1}},"children":[{"type":"text","value":"The software environment for this cookbook must be installed","position":{"start":{"line":32,"column":1},"end":{"line":32,"column":1}},"key":"kctOhpn6Fk"}],"urlSource":"https://github.com/ASFOpenSARlab/NISAR_GCOV_Cookbook/blob/main/notebooks/software_environment_docker.ipynb","data":{"kind":"file","org":"ASFOpenSARlab","repo":"NISAR_GCOV_Cookbook","reference":"main","file":"notebooks/software_environment_docker.ipynb","raw":"https://raw.githubusercontent.com/ASFOpenSARlab/NISAR_GCOV_Cookbook/main/notebooks/software_environment_docker.ipynb"},"internal":false,"protocol":"github","key":"cMIoGnYABo"}],"key":"h96h7nqmaK"},{"type":"tableCell","position":{"start":{"line":32,"column":1},"end":{"line":32,"column":1}},"children":[{"type":"text","value":"Necessary","position":{"start":{"line":32,"column":1},"end":{"line":32,"column":1}},"key":"BUnv7CEv4g"}],"key":"HFm8vC9fmo"},{"type":"tableCell","position":{"start":{"line":32,"column":1},"end":{"line":32,"column":1}},"children":[],"key":"HGe8rQP6lR"}],"key":"wbazh3Nnl9"}],"key":"i7aJdmy7dI"},{"type":"list","ordered":false,"spread":false,"position":{"start":{"line":34,"column":1},"end":{"line":35,"column":1}},"children":[{"type":"listItem","spread":true,"position":{"start":{"line":34,"column":1},"end":{"line":35,"column":1}},"children":[{"type":"paragraph","children":[{"type":"strong","position":{"start":{"line":34,"column":1},"end":{"line":34,"column":1}},"children":[{"type":"text","value":"Rough Notebook Time Estimate","position":{"start":{"line":34,"column":1},"end":{"line":34,"column":1}},"key":"zCy1gbYzbm"}],"key":"LblQl4jLRq"},{"type":"text","value":": 10 minutes","position":{"start":{"line":34,"column":1},"end":{"line":34,"column":1}},"key":"aEPcCNTz8b"}],"key":"ZxLCCETo1n"}],"key":"K5hGdOXjIF"}],"key":"xnMVm6wcw1"},{"type":"thematicBreak","key":"AD0tz0GyAk"}],"key":"cs9jUAk8mq"},{"type":"block","kind":"notebook-content","children":[{"type":"heading","depth":2,"position":{"start":{"line":2,"column":1},"end":{"line":2,"column":1}},"children":[{"type":"text","value":"2. Download a NISAR GCOV HDF5 file","position":{"start":{"line":2,"column":1},"end":{"line":2,"column":1}},"key":"a92BcM9wRR"}],"label":"hdf5-download","identifier":"hdf5-download","html_id":"hdf5-download","key":"TWMBCp9vKJ"},{"type":"paragraph","position":{"start":{"line":4,"column":1},"end":{"line":4,"column":1}},"children":[{"type":"text","value":"Download a GCOV HDF5 file to your home directory and view the top-level HDF5 group, ","position":{"start":{"line":4,"column":1},"end":{"line":4,"column":1}},"key":"U30wAMPAwd"},{"type":"inlineCode","value":"science","position":{"start":{"line":4,"column":1},"end":{"line":4,"column":1}},"key":"PkkDEyd3jM"},{"type":"text","value":".","position":{"start":{"line":4,"column":1},"end":{"line":4,"column":1}},"key":"EXIaqS8gKW"}],"key":"oCBDyqpmxO"},{"type":"heading","depth":3,"position":{"start":{"line":6,"column":1},"end":{"line":6,"column":1}},"children":[{"type":"text","value":"2a. Download the HDF5 file","position":{"start":{"line":6,"column":1},"end":{"line":6,"column":1}},"key":"lBXGcJycxW"}],"identifier":"id-2a-download-the-hdf5-file","label":"2a. Download the HDF5 file","html_id":"id-2a-download-the-hdf5-file","implicit":true,"key":"M1qrvabaul"}],"key":"Tidb6LViR0"},{"type":"block","kind":"notebook-code","children":[{"type":"code","lang":"python","executable":true,"value":"import os\nimport asf_search as asf\nfrom datetime import datetime\nfrom getpass import getpass\nfrom pathlib import Path\n\n#1: Search for and download NISAR GCOV HDF5 products from ASF\n\n#authenticate with Earthdata Login\n#create an ASF session object (stores your login + settings for requests)\nsession = asf.ASFSession()\n#prompt for username/password\nsession.auth_with_creds(input('EDL Username'), getpass('EDL Password'))\n\n#2: Define the search window and area of interest \n\n#insert start and end dates. Note that dates and times are inclusive. \nstart_date = datetime(2025, 12, 4)\nend_date = datetime(2025, 12, 5)\n# POINT or POLYGON as WKT (well-known-text) using lat/lon pairs \narea_of_interest = \"POLYGON((40.9131 12.3904,41.8891 12.3904,41.8891 13.2454,40.9131 13.2454,40.9131 12.3904))\" \n\n#3: Build search options \n\n#these filters narrow results to NISAR GCOV products over the AOI and time window\nopts = asf.ASFSearchOptions(\n    **{\n        \"maxResults\": 250,                    # cap the number of returned results\n        \"intersectsWith\": area_of_interest,   # spatial filter (WKT geometry)\n        \"start\": start_date,                  # temporal filter (start)\n        \"end\": end_date,                      # temporal filter (end)\n        \"processingLevel\": [\"GCOV\"],          # product type / processing level\n        \"dataset\": [\"NISAR\"],                 # mission/dataset name\n        \"productionConfiguration\": [\"PR\"],    # production config (e.g., provisional)\n        \"session\": session,                   # use authenticated session from above\n    }\n)\n\n#4: Run the search for HDF5 files\n#execute search\nresponse = asf.search(opts=opts)\n\n#exclude QA_STATE files \npattern = r'^(?!.*QA_STATS).*'\n\n#extract files that end with .h5 \nhdf5_files = response.find_urls(extension='.h5', pattern=pattern, directAccess=False)\nhdf5_files","key":"x4N1ToaBe8"},{"type":"outputs","id":"2ppl_WgzUO9O0iunUjTTu","children":[{"type":"output","jupyter_data":{"name":"stdin","output_type":"stream","text":"EDL Username aflewandowski\nEDL Password ········\n"},"children":[],"key":"huVEox9d1B"},{"type":"output","jupyter_data":{"output_type":"execute_result","execution_count":1,"metadata":{},"data":{"text/plain":{"content":"['https://nisar.asf.earthdatacloud.nasa.gov/NISAR/NISAR_L2_GCOV_BETA_V1/NISAR_L2_PR_GCOV_006_172_A_008_2005_DHDH_A_20251204T024618_20251204T024653_X05007_N_F_J_001/NISAR_L2_PR_GCOV_006_172_A_008_2005_DHDH_A_20251204T024618_20251204T024653_X05007_N_F_J_001.h5',\n 'https://nisar.asf.earthdatacloud.nasa.gov/NISAR/NISAR_L2_GCOV_BETA_V1/NISAR_L2_PR_GCOV_006_172_A_008_2005_DHDH_A_20251204T024618_20251204T024653_X05009_N_F_J_001/NISAR_L2_PR_GCOV_006_172_A_008_2005_DHDH_A_20251204T024618_20251204T024653_X05009_N_F_J_001.h5']","content_type":"text/plain"}}},"children":[],"key":"LlFS07vXYN"}],"key":"s9D2RlDCfV"}],"key":"ma0KRnsc8D"},{"type":"block","kind":"notebook-content","children":[{"type":"heading","depth":3,"position":{"start":{"line":1,"column":1},"end":{"line":1,"column":1}},"children":[{"type":"text","value":"2b. Retain only the URL for the most recent version of each product in the search results","position":{"start":{"line":1,"column":1},"end":{"line":1,"column":1}},"key":"rDlvWFRCuP"}],"identifier":"id-2b-retain-only-the-url-for-the-most-recent-version-of-each-product-in-the-search-results","label":"2b. Retain only the URL for the most recent version of each product in the search results","html_id":"id-2b-retain-only-the-url-for-the-most-recent-version-of-each-product-in-the-search-results","implicit":true,"key":"wjnCH9eJDg"},{"type":"paragraph","position":{"start":{"line":3,"column":1},"end":{"line":3,"column":1}},"children":[{"type":"text","value":"Data is occasionally re-released with an updated version. Versions are recorded as a ","position":{"start":{"line":3,"column":1},"end":{"line":3,"column":1}},"key":"pcbptLXFOk"},{"type":"link","url":"https://nisar-docs.asf.alaska.edu/naming-conventions/","position":{"start":{"line":3,"column":1},"end":{"line":3,"column":1}},"children":[{"type":"text","value":"Composite Release Identifier (CRID)","position":{"start":{"line":3,"column":1},"end":{"line":3,"column":1}},"key":"PiWmwdhQTc"}],"urlSource":"https://nisar-docs.asf.alaska.edu/naming-conventions/","key":"VYsmq0s4gt"},{"type":"text","value":" in a product’s filename. We can use the CRID to retain only the most recent version of each product in the list of URLs.","position":{"start":{"line":3,"column":1},"end":{"line":3,"column":1}},"key":"eYnhFvLg8D"}],"key":"kJthgfZ9x7"}],"key":"whk2Z9k8VQ"},{"type":"block","kind":"notebook-code","children":[{"type":"code","lang":"python","executable":true,"value":"import re\n\npattern = re.compile(r\"(NISAR_L2_PR_GCOV(?:_[^_]+){9})_(X\\d{5})\")\n\nlatest_version_dict = {}\n\nfor url in hdf5_files:\n    m = pattern.search(url)\n    if not m:\n        continue\n\n    product, crid = m.groups()\n\n    if product not in latest_version_dict or crid > latest_version_dict[product][0]:\n        latest_version_dict[product] = (crid, url)\n\nhdf5_files = [i[1] for i in latest_version_dict.values()]\nprint(f\"Retained {len(hdf5_files)} GCOV products:\")\nhdf5_files","key":"ey49HLxIiG"},{"type":"outputs","id":"s4pGo1Roho-rJRjREs1R5","children":[{"type":"output","jupyter_data":{"name":"stdout","output_type":"stream","text":"Retained 1 GCOV products:\n"},"children":[],"key":"Ti4t0OnRSW"},{"type":"output","jupyter_data":{"output_type":"execute_result","execution_count":2,"metadata":{},"data":{"text/plain":{"content":"['https://nisar.asf.earthdatacloud.nasa.gov/NISAR/NISAR_L2_GCOV_BETA_V1/NISAR_L2_PR_GCOV_006_172_A_008_2005_DHDH_A_20251204T024618_20251204T024653_X05009_N_F_J_001/NISAR_L2_PR_GCOV_006_172_A_008_2005_DHDH_A_20251204T024618_20251204T024653_X05009_N_F_J_001.h5']","content_type":"text/plain"}}},"children":[],"key":"JignzlbTcI"}],"key":"J4AQQPDFNh"}],"key":"j5ypnjvVt5"},{"type":"block","kind":"notebook-content","children":[{"type":"heading","depth":3,"position":{"start":{"line":1,"column":1},"end":{"line":1,"column":1}},"children":[{"type":"text","value":"2c. Download the data","position":{"start":{"line":1,"column":1},"end":{"line":1,"column":1}},"key":"RVknV3PvNB"}],"identifier":"id-2c-download-the-data","label":"2c. Download the data","html_id":"id-2c-download-the-data","implicit":true,"key":"hSyVWrE4HR"}],"key":"PvkF42Q7DM"},{"type":"block","kind":"notebook-code","children":[{"type":"code","lang":"python","executable":true,"value":"# Create a folder and download the files\ndata_dir = Path.home() / \"GCOV_data\"\ndata_dir.mkdir(exist_ok=True)\nprint(f'data_dir: {data_dir}')\n\n#download files\nasf.download_urls(hdf5_files, data_dir, session=session, processes=4)","key":"xjI0gg5U2b"},{"type":"outputs","id":"bnF1UQQZoY66mudz2xKqg","children":[{"type":"output","jupyter_data":{"name":"stdout","output_type":"stream","text":"data_dir: /home/jovyan/GCOV_data\n"},"children":[],"key":"vBzcRc41Q2"}],"key":"GkT1LtnKLq"}],"key":"g6NhIzOsd3"},{"type":"block","kind":"notebook-content","children":[{"type":"heading","depth":3,"position":{"start":{"line":1,"column":1},"end":{"line":1,"column":1}},"children":[{"type":"text","value":"2d. Open the file and list the top-level HDF5 group","position":{"start":{"line":1,"column":1},"end":{"line":1,"column":1}},"key":"yAb7IUK9xr"}],"identifier":"id-2d-open-the-file-and-list-the-top-level-hdf5-group","label":"2d. Open the file and list the top-level HDF5 group","html_id":"id-2d-open-the-file-and-list-the-top-level-hdf5-group","implicit":true,"key":"T655mMtggM"}],"key":"de08ran1ja"},{"type":"block","kind":"notebook-code","children":[{"type":"code","lang":"python","executable":true,"value":"import h5py\n\n#path to the NISAR GCOV HDF5 file\nh5_path = list(data_dir.glob(\"NISAR_L2_*_GCOV*.h5\"))[0]\n\n#open the GCOV HDF5 file in read mode (\"r\")\n#HDF5 files behave like Python dictionaries, where keys correspond to groups\nf = h5py.File(h5_path, \"r\")\n\n#inspect the top-level group names in the file\nlist(f)","key":"ij9p1ESgzP"},{"type":"outputs","id":"auh2tttdZKsFNHHtMMULU","children":[{"type":"output","jupyter_data":{"output_type":"execute_result","execution_count":4,"metadata":{},"data":{"text/plain":{"content":"['science']","content_type":"text/plain"}}},"children":[],"key":"WGRnGCHG9G"}],"key":"Xj0aM3zadC"}],"key":"DmZVOPqKUa"},{"type":"block","kind":"notebook-content","children":[{"type":"thematicBreak","key":"FHcHycQHdM"}],"key":"QlDXkrMDZf"},{"type":"block","kind":"notebook-content","children":[{"type":"heading","depth":2,"position":{"start":{"line":2,"column":1},"end":{"line":2,"column":1}},"children":[{"type":"text","value":"3. Accessing the science and LSAR groups","position":{"start":{"line":2,"column":1},"end":{"line":2,"column":1}},"key":"J0TgNj1eT7"}],"label":"hdf5-science","identifier":"hdf5-science","html_id":"hdf5-science","key":"ZQsPZC7CcC"},{"type":"paragraph","position":{"start":{"line":4,"column":1},"end":{"line":4,"column":1}},"children":[{"type":"text","value":"All NISAR science products organize their primary data and metadata under the ","position":{"start":{"line":4,"column":1},"end":{"line":4,"column":1}},"key":"wg69welcCY"},{"type":"inlineCode","value":"/science","position":{"start":{"line":4,"column":1},"end":{"line":4,"column":1}},"key":"z1gwDIRVUZ"},{"type":"text","value":" group. After opening the file, the first step in navigating a GCOV product is to inspect this group to determine which SAR instruments (LSAR only, or both SSAR and LSAR) are included in the file. This indicates available paths within the GCOV data.","position":{"start":{"line":4,"column":1},"end":{"line":4,"column":1}},"key":"dmwzX34JFm"}],"key":"hIcU1pXUoM"},{"type":"paragraph","position":{"start":{"line":6,"column":1},"end":{"line":6,"column":1}},"children":[{"type":"text","value":"In this notebook, we focus exclusively on GCOV data produced by the L-band SAR (LSAR) instrument.","position":{"start":{"line":6,"column":1},"end":{"line":6,"column":1}},"key":"YDxq0FxjdL"}],"key":"dBNtU1eAh7"}],"key":"ZUhO9fpY6Y"},{"type":"block","kind":"notebook-code","children":[{"type":"code","lang":"python","executable":true,"value":"list(f[\"science\"])","key":"W3WIydamfq"},{"type":"outputs","id":"NfRGwSS9vI6Tb0eQVswHq","children":[{"type":"output","jupyter_data":{"output_type":"execute_result","execution_count":5,"metadata":{},"data":{"text/plain":{"content":"['LSAR']","content_type":"text/plain"}}},"children":[],"key":"ENtkk1tkme"}],"key":"tLvxWD10zj"}],"key":"LObpOT5UEz"},{"type":"block","kind":"notebook-content","data":{"jp-MarkdownHeadingCollapsed":true},"children":[{"type":"details","children":[{"type":"summary","children":[{"type":"text","value":"Output Explanation","position":{"start":{"line":1,"column":1},"end":{"line":1,"column":1}},"key":"PDHttNPJhC"}],"key":"Mi7uR6dtyH"},{"type":"paragraph","position":{"start":{"line":3,"column":1},"end":{"line":3,"column":1}},"children":[{"type":"text","value":"The output of this command shows the available science subgroups within the file. Depending on the product and acquisition mode, a GCOV file may contain:","position":{"start":{"line":3,"column":1},"end":{"line":3,"column":1}},"key":"c0NoY47dak"}],"key":"YpDbAe5vL2"},{"type":"list","ordered":false,"spread":false,"position":{"start":{"line":5,"column":1},"end":{"line":8,"column":1}},"children":[{"type":"listItem","spread":true,"position":{"start":{"line":5,"column":1},"end":{"line":6,"column":1}},"children":[{"type":"paragraph","position":{"start":{"line":5,"column":1},"end":{"line":5,"column":1}},"children":[{"type":"text","value":"only ","position":{"start":{"line":5,"column":1},"end":{"line":5,"column":1}},"key":"q5DJQvBrgV"},{"type":"inlineCode","value":"LSAR","position":{"start":{"line":5,"column":1},"end":{"line":5,"column":1}},"key":"WXFmA3RN7G"},{"type":"text","value":": L-band SAR data, or","position":{"start":{"line":5,"column":1},"end":{"line":5,"column":1}},"key":"RqRKrmaSmz"}],"key":"GtphEceQfT"}],"key":"ZQXXGVFQX6"},{"type":"listItem","spread":true,"position":{"start":{"line":7,"column":1},"end":{"line":8,"column":1}},"children":[{"type":"paragraph","position":{"start":{"line":7,"column":1},"end":{"line":7,"column":1}},"children":[{"type":"text","value":"both ","position":{"start":{"line":7,"column":1},"end":{"line":7,"column":1}},"key":"UfT4naATrM"},{"type":"inlineCode","value":"LSAR","position":{"start":{"line":7,"column":1},"end":{"line":7,"column":1}},"key":"HAGbq4Zr1V"},{"type":"text","value":" and ","position":{"start":{"line":7,"column":1},"end":{"line":7,"column":1}},"key":"QuhW3awF4Y"},{"type":"inlineCode","value":"SSAR","position":{"start":{"line":7,"column":1},"end":{"line":7,"column":1}},"key":"cxiL30O3hR"},{"type":"text","value":": L-band and S-band SAR data","position":{"start":{"line":7,"column":1},"end":{"line":7,"column":1}},"key":"Oq6dEAXvyA"}],"key":"SnCCeAsB6B"}],"key":"GRsvZO0DY8"}],"key":"fTqkwGCcgm"},{"type":"paragraph","position":{"start":{"line":9,"column":1},"end":{"line":9,"column":1}},"children":[{"type":"inlineCode","value":"L-SAR","position":{"start":{"line":9,"column":1},"end":{"line":9,"column":1}},"key":"qRSMbZ6aSi"},{"type":"text","value":" and ","position":{"start":{"line":9,"column":1},"end":{"line":9,"column":1}},"key":"uMRzcVyoPO"},{"type":"inlineCode","value":"S-SAR","position":{"start":{"line":9,"column":1},"end":{"line":9,"column":1}},"key":"WUTb3XJRQs"},{"type":"text","value":" data are always stored in separate groups, even if they cover the same geographic area or acquisition time.","position":{"start":{"line":9,"column":1},"end":{"line":9,"column":1}},"key":"cGrjrxhdS3"}],"key":"E2Nl9MFuvC"}],"key":"KPwPMg04QF"}],"key":"oeSKoLLikQ"},{"type":"block","kind":"notebook-content","children":[{"type":"thematicBreak","key":"hl5xumnQaE"}],"key":"q33MDvqR7I"},{"type":"block","kind":"notebook-content","children":[{"type":"heading","depth":2,"position":{"start":{"line":2,"column":1},"end":{"line":2,"column":1}},"children":[{"type":"text","value":"4. Accessing the LSAR group","position":{"start":{"line":2,"column":1},"end":{"line":2,"column":1}},"key":"eOuCNzc44Z"}],"label":"hdf5-lsar","identifier":"hdf5-lsar","html_id":"hdf5-lsar","key":"jnEXiJbVtq"},{"type":"paragraph","position":{"start":{"line":4,"column":1},"end":{"line":4,"column":1}},"children":[{"type":"text","value":"Within the ","position":{"start":{"line":4,"column":1},"end":{"line":4,"column":1}},"key":"u0HyuqIHKK"},{"type":"inlineCode","value":"/science/LSAR","position":{"start":{"line":4,"column":1},"end":{"line":4,"column":1}},"key":"NIrfCR26br"},{"type":"text","value":"/ group, different product types and supporting information are organized into separate subgroups. For GCOV products, all gridded covariance data are stored under the ","position":{"start":{"line":4,"column":1},"end":{"line":4,"column":1}},"key":"mnmfLCjFWF"},{"type":"inlineCode","value":"/science/LSAR/GCOV/","position":{"start":{"line":4,"column":1},"end":{"line":4,"column":1}},"key":"MPrzNfRrvc"},{"type":"text","value":" path.","position":{"start":{"line":4,"column":1},"end":{"line":4,"column":1}},"key":"Oe4x3fUJh1"}],"key":"tkg2HToLvk"},{"type":"paragraph","position":{"start":{"line":6,"column":1},"end":{"line":6,"column":1}},"children":[{"type":"text","value":"The next step is to inspect the contents of the ","position":{"start":{"line":6,"column":1},"end":{"line":6,"column":1}},"key":"SQlxkbaRAn"},{"type":"inlineCode","value":"/science/LSAR/","position":{"start":{"line":6,"column":1},"end":{"line":6,"column":1}},"key":"sLR1FDvnqZ"},{"type":"text","value":" group to confirm the presence of the GCOV subgroup.","position":{"start":{"line":6,"column":1},"end":{"line":6,"column":1}},"key":"AgBCu4XhNf"}],"key":"jGM9RBB1LD"}],"key":"uOpCwnYWj0"},{"type":"block","kind":"notebook-code","children":[{"type":"code","lang":"python","executable":true,"value":"#list the contents of the /science/LSAR group\n#this shows the available product types and supporting subgroups\nlist(f[\"science/LSAR\"])","key":"nnW3ele28Y"},{"type":"outputs","id":"c_K1T3X4Qjs41UM4Ku9JZ","children":[{"type":"output","jupyter_data":{"output_type":"execute_result","execution_count":6,"metadata":{},"data":{"text/plain":{"content":"['GCOV', 'identification']","content_type":"text/plain"}}},"children":[],"key":"WGlTtsV9UQ"}],"key":"KD10x6Ubg6"}],"key":"gzBCEsTU89"},{"type":"block","kind":"notebook-content","children":[{"type":"details","children":[{"type":"summary","children":[{"type":"text","value":"Output Explanation","position":{"start":{"line":1,"column":1},"end":{"line":1,"column":1}},"key":"Ql5wtGSGU0"}],"key":"gE3mFKHjQI"},{"type":"paragraph","position":{"start":{"line":2,"column":1},"end":{"line":2,"column":1}},"children":[{"type":"text","value":"The ","position":{"start":{"line":2,"column":1},"end":{"line":2,"column":1}},"key":"swEvv8PI3F"},{"type":"inlineCode","value":"/science/LSAR/","position":{"start":{"line":2,"column":1},"end":{"line":2,"column":1}},"key":"TZzZwAj3HC"},{"type":"text","value":" group contains two subgroups:","position":{"start":{"line":2,"column":1},"end":{"line":2,"column":1}},"key":"YsfC4fZJwv"}],"key":"Zq8o8R85lu"},{"type":"list","ordered":false,"spread":false,"position":{"start":{"line":4,"column":1},"end":{"line":7,"column":1}},"children":[{"type":"listItem","spread":true,"position":{"start":{"line":4,"column":1},"end":{"line":5,"column":1}},"children":[{"type":"paragraph","position":{"start":{"line":4,"column":1},"end":{"line":4,"column":1}},"children":[{"type":"inlineCode","value":"GCOV","position":{"start":{"line":4,"column":1},"end":{"line":4,"column":1}},"key":"A1X2135dnP"},{"type":"text","value":": the gridded covariance product data","position":{"start":{"line":4,"column":1},"end":{"line":4,"column":1}},"key":"M59zHHQCxG"}],"key":"xV7CJBm9Zg"}],"key":"gDn1fEiFE8"},{"type":"listItem","spread":true,"position":{"start":{"line":6,"column":1},"end":{"line":7,"column":1}},"children":[{"type":"paragraph","position":{"start":{"line":6,"column":1},"end":{"line":6,"column":1}},"children":[{"type":"inlineCode","value":"identification","position":{"start":{"line":6,"column":1},"end":{"line":6,"column":1}},"key":"SPFPDlhsp1"},{"type":"text","value":": granule-level metadata describing the acquisition and processing of this product","position":{"start":{"line":6,"column":1},"end":{"line":6,"column":1}},"key":"dR6CkD5Pi7"}],"key":"AvZNeD6WhF"}],"key":"JFWLx7b5WW"}],"key":"gWbVW7bDoO"},{"type":"paragraph","position":{"start":{"line":8,"column":1},"end":{"line":8,"column":1}},"children":[{"type":"text","value":"The presence of the GCOV group confirms that this file contains GCOV data, and indicates where the gridded raster datasets are stored. The identification group contains supporting metadata and is useful for context, but note that it does not contain raster data.","position":{"start":{"line":8,"column":1},"end":{"line":8,"column":1}},"key":"dRhK6T9Hd6"}],"key":"BQggyGcQmv"}],"key":"f7o1L0dFol"}],"key":"DJND2lNRrz"},{"type":"block","kind":"notebook-content","children":[{"type":"thematicBreak","key":"nEIAHcGqNw"}],"key":"IMsXIGUNFm"},{"type":"block","kind":"notebook-content","children":[{"type":"heading","depth":2,"position":{"start":{"line":2,"column":1},"end":{"line":2,"column":1}},"children":[{"type":"text","value":"5. Accessing the GCOV group","position":{"start":{"line":2,"column":1},"end":{"line":2,"column":1}},"key":"sVU7JMQ2lp"}],"label":"hdf5-gcov","identifier":"hdf5-gcov","html_id":"hdf5-gcov","key":"hoLFzNX6Z2"},{"type":"paragraph","position":{"start":{"line":4,"column":1},"end":{"line":4,"column":1}},"children":[{"type":"text","value":"After confirming that the file contains GCOV data, the next step is to examine how the GCOV product is organized internally. The ","position":{"start":{"line":4,"column":1},"end":{"line":4,"column":1}},"key":"O2T5XTNFkS"},{"type":"inlineCode","value":"GCOV","position":{"start":{"line":4,"column":1},"end":{"line":4,"column":1}},"key":"kdZZn7FZYG"},{"type":"text","value":" group serves as the top-level container for all gridded covariance data and related metadata within the LSAR science product.","position":{"start":{"line":4,"column":1},"end":{"line":4,"column":1}},"key":"TR26tFbW6e"}],"key":"YpXPnOvS8j"},{"type":"paragraph","position":{"start":{"line":6,"column":1},"end":{"line":6,"column":1}},"children":[{"type":"text","value":"Listing the contents of the ","position":{"start":{"line":6,"column":1},"end":{"line":6,"column":1}},"key":"t6aC4QEpUO"},{"type":"inlineCode","value":"GCOV","position":{"start":{"line":6,"column":1},"end":{"line":6,"column":1}},"key":"m20boaKGbH"},{"type":"text","value":" group allows us to identify where the gridded measurement datasets are stored and which subgroups contain supporting information.","position":{"start":{"line":6,"column":1},"end":{"line":6,"column":1}},"key":"j7pGZm670W"}],"key":"CI97vO64wl"}],"key":"oIuVpONa4C"},{"type":"block","kind":"notebook-code","children":[{"type":"code","lang":"python","executable":true,"value":"#list the contents of the GCOV group\n#this reveals how GCOV data are organized internally\nlist(f[\"science/LSAR/GCOV\"])","key":"CVBskYZ0Vt"},{"type":"outputs","id":"E-43DDTr-Troaih9jhz0d","children":[{"type":"output","jupyter_data":{"output_type":"execute_result","execution_count":7,"metadata":{},"data":{"text/plain":{"content":"['grids', 'metadata']","content_type":"text/plain"}}},"children":[],"key":"v8p5Yw9uFH"}],"key":"XFKW2aY7t4"}],"key":"UbP8wif2uZ"},{"type":"block","kind":"notebook-content","children":[{"type":"details","children":[{"type":"summary","children":[{"type":"text","value":"Output Explanation","position":{"start":{"line":1,"column":1},"end":{"line":1,"column":1}},"key":"xJdcRXXjix"}],"key":"EJNNADWhc1"},{"type":"paragraph","position":{"start":{"line":2,"column":1},"end":{"line":2,"column":1}},"children":[{"type":"text","value":"The GCOV group is organized into two primary subgroups:","position":{"start":{"line":2,"column":1},"end":{"line":2,"column":1}},"key":"TmQQQhJ7Df"}],"key":"YO22nqkphR"},{"type":"list","ordered":false,"spread":false,"position":{"start":{"line":4,"column":1},"end":{"line":7,"column":1}},"children":[{"type":"listItem","spread":true,"position":{"start":{"line":4,"column":1},"end":{"line":5,"column":1}},"children":[{"type":"paragraph","position":{"start":{"line":4,"column":1},"end":{"line":4,"column":1}},"children":[{"type":"inlineCode","value":"grids","position":{"start":{"line":4,"column":1},"end":{"line":4,"column":1}},"key":"qLqpPcGifU"},{"type":"text","value":": contains the gridded covariance datasets and related raster-style data","position":{"start":{"line":4,"column":1},"end":{"line":4,"column":1}},"key":"IZXZYmBoCc"}],"key":"g9o6yslmpO"}],"key":"szDcbVeaTL"},{"type":"listItem","spread":true,"position":{"start":{"line":6,"column":1},"end":{"line":7,"column":1}},"children":[{"type":"paragraph","position":{"start":{"line":6,"column":1},"end":{"line":6,"column":1}},"children":[{"type":"inlineCode","value":"metadata","position":{"start":{"line":6,"column":1},"end":{"line":6,"column":1}},"key":"oi6OvXGkqx"},{"type":"text","value":": contains product-level metadata specific to the GCOV product","position":{"start":{"line":6,"column":1},"end":{"line":6,"column":1}},"key":"OQxuUekHJ5"}],"key":"OcMTt4uvT7"}],"key":"tMLIUvWaq3"}],"key":"c6R6MJXMFM"},{"type":"paragraph","position":{"start":{"line":8,"column":1},"end":{"line":8,"column":1}},"children":[{"type":"text","value":"All GCOV raster data that is commonly visualized or analyzed are stored under the grids group. The metadata group provides supporting information but does not contain gridded measurement arrays.","position":{"start":{"line":8,"column":1},"end":{"line":8,"column":1}},"key":"XlDGz8ff15"}],"key":"d05e6asPo0"}],"key":"Kxab0YMXzx"}],"key":"Fvx3NWFncx"},{"type":"block","kind":"notebook-content","children":[{"type":"thematicBreak","key":"nPtngpcJwB"}],"key":"dcaxjrB52C"},{"type":"block","kind":"notebook-content","children":[{"type":"heading","depth":2,"position":{"start":{"line":2,"column":1},"end":{"line":2,"column":1}},"children":[{"type":"text","value":"6. Navigating into the grids group","position":{"start":{"line":2,"column":1},"end":{"line":2,"column":1}},"key":"sexH9tqEUf"}],"label":"hdf5-grids","identifier":"hdf5-grids","html_id":"hdf5-grids","key":"A18s4cyftB"},{"type":"paragraph","position":{"start":{"line":3,"column":1},"end":{"line":3,"column":1}},"children":[{"type":"text","value":"The contents of the ","position":{"start":{"line":3,"column":1},"end":{"line":3,"column":1}},"key":"GwaXr9UeTz"},{"type":"inlineCode","value":"grids","position":{"start":{"line":3,"column":1},"end":{"line":3,"column":1}},"key":"g2wh8hMDp0"},{"type":"text","value":" group inform which frequency groups are present in the GCOV product. Depending on the acquisition mode, a GCOV file may contain data from one or two frequency groups.","position":{"start":{"line":3,"column":1},"end":{"line":3,"column":1}},"key":"jJBhxc622l"}],"key":"l9Z3fNuyXQ"}],"key":"gdp9TXIIvo"},{"type":"block","kind":"notebook-code","children":[{"type":"code","lang":"python","executable":true,"value":"#list the contents of the grids group\n#this shows how GCOV raster data are organized by frequency\nlist(f[\"science/LSAR/GCOV/grids\"])","key":"cMQWa1nQvL"},{"type":"outputs","id":"J28JQs7YUwne_O9ZB59wG","children":[{"type":"output","jupyter_data":{"output_type":"execute_result","execution_count":8,"metadata":{},"data":{"text/plain":{"content":"['frequencyA', 'frequencyB']","content_type":"text/plain"}}},"children":[],"key":"KmM5CaMhX7"}],"key":"p8SnWpDtkC"}],"key":"xfIyJM2SBg"},{"type":"block","kind":"notebook-content","children":[{"type":"details","children":[{"type":"summary","children":[{"type":"text","value":"Output Explanation","position":{"start":{"line":1,"column":1},"end":{"line":1,"column":1}},"key":"CdcQezubsP"}],"key":"UQDMuWxX8X"},{"type":"paragraph","position":{"start":{"line":2,"column":1},"end":{"line":2,"column":1}},"children":[{"type":"text","value":"GCOV raster datasets are grouped by frequency band within the ","position":{"start":{"line":2,"column":1},"end":{"line":2,"column":1}},"key":"NyG1Vx1Vt4"},{"type":"inlineCode","value":"grids","position":{"start":{"line":2,"column":1},"end":{"line":2,"column":1}},"key":"YsBjLX9OEi"},{"type":"text","value":" group. The two frequency groups represent different portions of the radar bandwidth:","position":{"start":{"line":2,"column":1},"end":{"line":2,"column":1}},"key":"M1GzpFctrP"}],"key":"XdZMnjboyG"},{"type":"list","ordered":false,"spread":false,"position":{"start":{"line":4,"column":1},"end":{"line":7,"column":1}},"children":[{"type":"listItem","spread":true,"position":{"start":{"line":4,"column":1},"end":{"line":5,"column":1}},"children":[{"type":"paragraph","position":{"start":{"line":4,"column":1},"end":{"line":4,"column":1}},"children":[{"type":"inlineCode","value":"frequencyA","position":{"start":{"line":4,"column":1},"end":{"line":4,"column":1}},"key":"t09Ly1L5Bl"},{"type":"text","value":": datasets derived from the lower portion of the LSAR bandwidth","position":{"start":{"line":4,"column":1},"end":{"line":4,"column":1}},"key":"WCOpSnfOb6"}],"key":"fDGixa85ep"}],"key":"PhMiWcAMBb"},{"type":"listItem","spread":true,"position":{"start":{"line":6,"column":1},"end":{"line":7,"column":1}},"children":[{"type":"paragraph","position":{"start":{"line":6,"column":1},"end":{"line":6,"column":1}},"children":[{"type":"inlineCode","value":"frequencyB","position":{"start":{"line":6,"column":1},"end":{"line":6,"column":1}},"key":"wtUKNyUddI"},{"type":"text","value":": datasets derived from the higher portion of the LSAR bandwidth","position":{"start":{"line":6,"column":1},"end":{"line":6,"column":1}},"key":"yKnWn39tzb"}],"key":"w7gjpOW1cn"}],"key":"Q7E3xFbnn4"}],"key":"drMVKSjTDG"},{"type":"paragraph","position":{"start":{"line":8,"column":1},"end":{"line":8,"column":1}},"children":[{"type":"text","value":"Depending on the acquisition mode, a GCOV product may contain data from only one frequency group or from both ","position":{"start":{"line":8,"column":1},"end":{"line":8,"column":1}},"key":"qfYoAV9sbL"},{"type":"inlineCode","value":"frequencyA","position":{"start":{"line":8,"column":1},"end":{"line":8,"column":1}},"key":"YbbbgAQ8U6"},{"type":"text","value":" and ","position":{"start":{"line":8,"column":1},"end":{"line":8,"column":1}},"key":"pzERH1NBha"},{"type":"inlineCode","value":"frequencyB","position":{"start":{"line":8,"column":1},"end":{"line":8,"column":1}},"key":"cxEtn8Fgp8"},{"type":"text","value":". The presence of both groups indicates that this product includes measurements from two portions of the L-SAR spectrum.","position":{"start":{"line":8,"column":1},"end":{"line":8,"column":1}},"key":"mxoZQaY6vt"}],"key":"EG0EiC1UKq"}],"key":"ikZrYI73tw"}],"key":"jL8vZutciZ"},{"type":"block","kind":"notebook-content","children":[{"type":"thematicBreak","key":"XLNsDLshJP"}],"key":"I6MLO8KV1r"},{"type":"block","kind":"notebook-content","children":[{"type":"heading","depth":2,"position":{"start":{"line":2,"column":1},"end":{"line":2,"column":1}},"children":[{"type":"text","value":"7. Inspecting datasets within a frequency group","position":{"start":{"line":2,"column":1},"end":{"line":2,"column":1}},"key":"ggHLauotpm"}],"label":"hdf5-frequency","identifier":"hdf5-frequency","html_id":"hdf5-frequency","key":"t75TMLBexv"},{"type":"paragraph","position":{"start":{"line":4,"column":1},"end":{"line":4,"column":1}},"children":[{"type":"text","value":"The next step is to list the datasets available for a specific frequency group. In this example, we inspect ","position":{"start":{"line":4,"column":1},"end":{"line":4,"column":1}},"key":"q0rjI7RDdS"},{"type":"inlineCode","value":"frequencyA","position":{"start":{"line":4,"column":1},"end":{"line":4,"column":1}},"key":"MpWcFASyaG"},{"type":"text","value":".","position":{"start":{"line":4,"column":1},"end":{"line":4,"column":1}},"key":"LqlewldOI0"}],"key":"w676DQfzqF"}],"key":"dCAY5higrH"},{"type":"block","kind":"notebook-code","children":[{"type":"code","lang":"python","executable":true,"value":"#list the datasets available within the frequencyA group\n#these correspond to specific polarization combinations and supporting layers\nlist(f[\"science/LSAR/GCOV/grids/frequencyA\"])","key":"sGOUTNWap7"},{"type":"outputs","id":"_UbBc-2Kyp7cqc5a9tLA2","children":[{"type":"output","jupyter_data":{"output_type":"execute_result","execution_count":9,"metadata":{},"data":{"text/plain":{"content":"['HHHH',\n 'HVHV',\n 'listOfCovarianceTerms',\n 'listOfPolarizations',\n 'mask',\n 'numberOfLooks',\n 'numberOfSubSwaths',\n 'projection',\n 'rtcGammaToSigmaFactor',\n 'xCoordinateSpacing',\n 'xCoordinates',\n 'yCoordinateSpacing',\n 'yCoordinates']","content_type":"text/plain"}}},"children":[],"key":"g7UNfZej0S"}],"key":"wTqpv7ZZHT"}],"key":"M1pfOjT1bL"},{"type":"block","kind":"notebook-content","children":[{"type":"details","children":[{"type":"summary","children":[{"type":"text","value":"Output Explanation","position":{"start":{"line":1,"column":1},"end":{"line":1,"column":1}},"key":"p0deUW8Mcf"}],"key":"aMr96knzLC"},{"type":"heading","depth":4,"position":{"start":{"line":2,"column":1},"end":{"line":2,"column":1}},"children":[{"type":"text","value":"1. Gridded covariance (measurement) datasets","position":{"start":{"line":2,"column":1},"end":{"line":2,"column":1}},"key":"aTUZTl3IQO"}],"identifier":"id-1-gridded-covariance-measurement-datasets","label":"1. Gridded covariance (measurement) datasets","html_id":"id-1-gridded-covariance-measurement-datasets","implicit":true,"key":"mUfgeDBWSr"},{"type":"paragraph","position":{"start":{"line":4,"column":1},"end":{"line":4,"column":1}},"children":[{"type":"text","value":"These datasets contain the primary GCOV raster data and represent specific polarization combinations. Examples include:","position":{"start":{"line":4,"column":1},"end":{"line":4,"column":1}},"key":"N54JAEt8v1"}],"key":"JCdYoC3QbV"},{"type":"list","ordered":false,"spread":false,"position":{"start":{"line":6,"column":1},"end":{"line":7,"column":1}},"children":[{"type":"listItem","spread":true,"position":{"start":{"line":6,"column":1},"end":{"line":7,"column":1}},"children":[{"type":"paragraph","children":[{"type":"inlineCode","value":"HHHH","position":{"start":{"line":6,"column":1},"end":{"line":6,"column":1}},"key":"JlBsKNU1HI"},{"type":"text","value":", ","position":{"start":{"line":6,"column":1},"end":{"line":6,"column":1}},"key":"q6M7mcLdxV"},{"type":"inlineCode","value":"HVHV","position":{"start":{"line":6,"column":1},"end":{"line":6,"column":1}},"key":"bxc3JYH403"},{"type":"text","value":": real-valued covariance terms","position":{"start":{"line":6,"column":1},"end":{"line":6,"column":1}},"key":"O3B67jpZeL"}],"key":"bhuVFROFSO"}],"key":"iIHOGR0SgD"}],"key":"HdJ1KdvAgJ"},{"type":"paragraph","position":{"start":{"line":8,"column":1},"end":{"line":8,"column":1}},"children":[{"type":"text","value":"Other products may also include cross-polarized or complex-valued terms. These datasets are commonly extracted, visualized, or converted to raster formats.","position":{"start":{"line":8,"column":1},"end":{"line":8,"column":1}},"key":"tk3hBEeFEU"}],"key":"lXfQOi2OdW"},{"type":"heading","depth":4,"position":{"start":{"line":10,"column":1},"end":{"line":10,"column":1}},"children":[{"type":"text","value":"2. Supporting raster layers","position":{"start":{"line":10,"column":1},"end":{"line":10,"column":1}},"key":"q5JJKEXPCd"}],"identifier":"id-2-supporting-raster-layers","label":"2. Supporting raster layers","html_id":"id-2-supporting-raster-layers","implicit":true,"key":"aa9nebzBVy"},{"type":"paragraph","position":{"start":{"line":12,"column":1},"end":{"line":12,"column":1}},"children":[{"type":"text","value":"These datasets provide information needed to interpret or process radar measurement data:","position":{"start":{"line":12,"column":1},"end":{"line":12,"column":1}},"key":"W5FUTaeYDR"}],"key":"V8JfStCBew"},{"type":"list","ordered":false,"spread":false,"position":{"start":{"line":14,"column":1},"end":{"line":19,"column":1}},"children":[{"type":"listItem","spread":true,"position":{"start":{"line":14,"column":1},"end":{"line":15,"column":1}},"children":[{"type":"paragraph","position":{"start":{"line":14,"column":1},"end":{"line":14,"column":1}},"children":[{"type":"inlineCode","value":"numberOfLooks","position":{"start":{"line":14,"column":1},"end":{"line":14,"column":1}},"key":"J8RwnzXlNo"},{"type":"text","value":": effective number of looks for each pixel","position":{"start":{"line":14,"column":1},"end":{"line":14,"column":1}},"key":"oeU6QRftO4"}],"key":"jruy7GPYgC"}],"key":"R3vxdGqwkY"},{"type":"listItem","spread":true,"position":{"start":{"line":16,"column":1},"end":{"line":17,"column":1}},"children":[{"type":"paragraph","position":{"start":{"line":16,"column":1},"end":{"line":16,"column":1}},"children":[{"type":"inlineCode","value":"rtcGammaToSigmaFactor","position":{"start":{"line":16,"column":1},"end":{"line":16,"column":1}},"key":"mjzhYx47p3"},{"type":"text","value":": factor used to convert radiometrically terrain-corrected gamma values to sigma-naught","position":{"start":{"line":16,"column":1},"end":{"line":16,"column":1}},"key":"IbUlYRiQ9E"}],"key":"OQSCi5vSt9"}],"key":"ywQLRzR6R5"},{"type":"listItem","spread":true,"position":{"start":{"line":18,"column":1},"end":{"line":19,"column":1}},"children":[{"type":"paragraph","position":{"start":{"line":18,"column":1},"end":{"line":18,"column":1}},"children":[{"type":"inlineCode","value":"mask","position":{"start":{"line":18,"column":1},"end":{"line":18,"column":1}},"key":"HgeOJCll68"},{"type":"text","value":": identifies valid and invalid pixels","position":{"start":{"line":18,"column":1},"end":{"line":18,"column":1}},"key":"Dl53LXW7md"}],"key":"b9f8bSEFh5"}],"key":"LVHBjkL2S1"}],"key":"uoG7GIHQQo"},{"type":"paragraph","position":{"start":{"line":20,"column":1},"end":{"line":20,"column":1}},"children":[{"type":"text","value":"These layers are spatially aligned with the covariance datasets.","position":{"start":{"line":20,"column":1},"end":{"line":20,"column":1}},"key":"kwyrWSoheP"}],"key":"hR1K3oAmzp"},{"type":"heading","depth":4,"position":{"start":{"line":22,"column":1},"end":{"line":22,"column":1}},"children":[{"type":"text","value":"3. Grid and coordinate information","position":{"start":{"line":22,"column":1},"end":{"line":22,"column":1}},"key":"R3dAQ0mKzq"}],"identifier":"id-3-grid-and-coordinate-information","label":"3. Grid and coordinate information","html_id":"id-3-grid-and-coordinate-information","implicit":true,"key":"Yt6dAZmS73"},{"type":"paragraph","position":{"start":{"line":24,"column":1},"end":{"line":24,"column":1}},"children":[{"type":"text","value":"These datasets define the spatial reference of the GCOV grids:","position":{"start":{"line":24,"column":1},"end":{"line":24,"column":1}},"key":"bbNfN7RJGJ"}],"key":"znRduaTYix"},{"type":"list","ordered":false,"spread":false,"position":{"start":{"line":26,"column":1},"end":{"line":30,"column":1}},"children":[{"type":"listItem","spread":true,"position":{"start":{"line":26,"column":1},"end":{"line":27,"column":1}},"children":[{"type":"paragraph","position":{"start":{"line":26,"column":1},"end":{"line":26,"column":1}},"children":[{"type":"inlineCode","value":"xCoordinates","position":{"start":{"line":26,"column":1},"end":{"line":26,"column":1}},"key":"tblmwU0cAF"},{"type":"text","value":", ","position":{"start":{"line":26,"column":1},"end":{"line":26,"column":1}},"key":"atCwkVM42j"},{"type":"inlineCode","value":"yCoordinates","position":{"start":{"line":26,"column":1},"end":{"line":26,"column":1}},"key":"NFH8lh8nMI"},{"type":"text","value":": coordinate vectors defining the grid","position":{"start":{"line":26,"column":1},"end":{"line":26,"column":1}},"key":"XFVMex3xWd"}],"key":"hzEeaLc8Ym"}],"key":"GAFE5rI9hk"},{"type":"listItem","spread":true,"position":{"start":{"line":28,"column":1},"end":{"line":29,"column":1}},"children":[{"type":"paragraph","position":{"start":{"line":28,"column":1},"end":{"line":28,"column":1}},"children":[{"type":"inlineCode","value":"xCoordinateSpacing","position":{"start":{"line":28,"column":1},"end":{"line":28,"column":1}},"key":"hHvRrSHF5Y"},{"type":"text","value":", ","position":{"start":{"line":28,"column":1},"end":{"line":28,"column":1}},"key":"SyTPHTTZkw"},{"type":"inlineCode","value":"yCoordinateSpacing","position":{"start":{"line":28,"column":1},"end":{"line":28,"column":1}},"key":"WL4Jvxfeat"},{"type":"text","value":": grid spacing","position":{"start":{"line":28,"column":1},"end":{"line":28,"column":1}},"key":"Z17UbA1tBU"}],"key":"cmnzmWPh8m"}],"key":"xPWapxKYqJ"},{"type":"listItem","spread":true,"position":{"start":{"line":30,"column":1},"end":{"line":30,"column":1}},"children":[{"type":"paragraph","position":{"start":{"line":30,"column":1},"end":{"line":30,"column":1}},"children":[{"type":"inlineCode","value":"projection","position":{"start":{"line":30,"column":1},"end":{"line":30,"column":1}},"key":"yJIwZ5XQKm"},{"type":"text","value":": map projection information","position":{"start":{"line":30,"column":1},"end":{"line":30,"column":1}},"key":"MTuWqTx3jw"}],"key":"i36ZC8gLNQ"}],"key":"gi2IDWrfVm"}],"key":"AZ3z5bMoUn"}],"key":"oAKXCOYcdb"}],"key":"MfSSTiB8Dh"},{"type":"block","kind":"notebook-content","children":[{"type":"thematicBreak","key":"db6zVXO8LX"}],"key":"pE0Be0qQCI"},{"type":"block","kind":"notebook-content","children":[{"type":"heading","depth":2,"position":{"start":{"line":2,"column":1},"end":{"line":2,"column":1}},"children":[{"type":"text","value":"8. Accessing a specific GCOV dataset","position":{"start":{"line":2,"column":1},"end":{"line":2,"column":1}},"key":"EgHXGAl6Ug"}],"label":"hdf5-gcov_dataset","identifier":"hdf5-gcov_dataset","html_id":"hdf5-gcov-dataset","key":"zFBDwqt4PE"},{"type":"paragraph","position":{"start":{"line":4,"column":1},"end":{"line":4,"column":1}},"children":[{"type":"text","value":"Once the available datasets within a frequency group have been identified, the next step is to access an individual dataset directly. Before loading the full raster into memory, it is useful to inspect basic properties of the dataset, such as its corresponding shape and data type, to confirm that it contains the expected data.","position":{"start":{"line":4,"column":1},"end":{"line":4,"column":1}},"key":"lxLnA8KjXA"}],"key":"PtBPLsZE7y"},{"type":"paragraph","position":{"start":{"line":6,"column":1},"end":{"line":6,"column":1}},"children":[{"type":"text","value":"In this example, we access the ","position":{"start":{"line":6,"column":1},"end":{"line":6,"column":1}},"key":"RBMsEXUozV"},{"type":"inlineCode","value":"HVHV","position":{"start":{"line":6,"column":1},"end":{"line":6,"column":1}},"key":"uCo0509aHt"},{"type":"text","value":" dataset from the ","position":{"start":{"line":6,"column":1},"end":{"line":6,"column":1}},"key":"pOsESUsnBl"},{"type":"inlineCode","value":"frequencyA","position":{"start":{"line":6,"column":1},"end":{"line":6,"column":1}},"key":"vGGGgIwbbj"},{"type":"text","value":" group.","position":{"start":{"line":6,"column":1},"end":{"line":6,"column":1}},"key":"bLaQyJOMbK"}],"key":"P4uI1QKeNT"}],"key":"tyt79oDD56"},{"type":"block","kind":"notebook-code","children":[{"type":"code","lang":"python","executable":true,"value":"#access a covariance (measurement) dataset by its full HDF5 path\n#HVHV is a real-valued covariance term for the HV–HV polarization combination\nhvhv = f[\"science/LSAR/GCOV/grids/frequencyA/HVHV\"]\n\n#inspect basic properties of the dataset without loading the full array\nhvhv.shape, hvhv.dtype","key":"SCXfU9MrD9"},{"type":"outputs","id":"tTv2WB1hPC0zWFkMY-7BG","children":[{"type":"output","jupyter_data":{"output_type":"execute_result","execution_count":10,"metadata":{},"data":{"text/plain":{"content":"((16704, 17064), dtype('<f4'))","content_type":"text/plain"}}},"children":[],"key":"J3xX3jmJXJ"}],"key":"TlKhU6E8Sd"}],"key":"igoRjkFNKF"},{"type":"block","kind":"notebook-content","children":[{"type":"details","children":[{"type":"summary","children":[{"type":"text","value":"Output Explanation","position":{"start":{"line":1,"column":1},"end":{"line":1,"column":1}},"key":"SdZJIxw2DF"}],"key":"D5WzsFPZRF"},{"type":"list","ordered":false,"spread":false,"position":{"start":{"line":3,"column":1},"end":{"line":8,"column":1}},"children":[{"type":"listItem","spread":true,"position":{"start":{"line":3,"column":1},"end":{"line":4,"column":1}},"children":[{"type":"paragraph","position":{"start":{"line":3,"column":1},"end":{"line":3,"column":1}},"children":[{"type":"text","value":"The ","position":{"start":{"line":3,"column":1},"end":{"line":3,"column":1}},"key":"tx9X823f2m"},{"type":"inlineCode","value":"HVHV","position":{"start":{"line":3,"column":1},"end":{"line":3,"column":1}},"key":"GTynsUWcnA"},{"type":"text","value":" object is an HDF5 dataset representing a gridded covariance measurement.","position":{"start":{"line":3,"column":1},"end":{"line":3,"column":1}},"key":"YR4Ve1zAUw"}],"key":"i31wMHRRK2"}],"key":"d0by1de0DE"},{"type":"listItem","spread":true,"position":{"start":{"line":5,"column":1},"end":{"line":6,"column":1}},"children":[{"type":"paragraph","position":{"start":{"line":5,"column":1},"end":{"line":5,"column":1}},"children":[{"type":"text","value":"The shape (16704, 17064) indicates the number of rows (16704) and columns (17064) in the raster grid.","position":{"start":{"line":5,"column":1},"end":{"line":5,"column":1}},"key":"fMvdIAm6gW"}],"key":"fEdpBsuxHv"}],"key":"OkUvKYyn0W"},{"type":"listItem","spread":true,"position":{"start":{"line":7,"column":1},"end":{"line":8,"column":1}},"children":[{"type":"paragraph","position":{"start":{"line":7,"column":1},"end":{"line":7,"column":1}},"children":[{"type":"text","value":"The data type (‘<f4’) describes how the values are stored (in this example, 32-bit floating point).","position":{"start":{"line":7,"column":1},"end":{"line":7,"column":1}},"key":"k0qTpItEez"}],"key":"IO1ixPAwAS"}],"key":"rlvZF0Juqj"}],"key":"NbqdZXZ4BF"},{"type":"paragraph","position":{"start":{"line":9,"column":1},"end":{"line":9,"column":1}},"children":[{"type":"text","value":"Accessing these properties does not load the full dataset into memory, making this a safe way to verify dataset contents before reading the data values.","position":{"start":{"line":9,"column":1},"end":{"line":9,"column":1}},"key":"bmej4fNGfG"}],"key":"Mpy3KS6WqE"}],"key":"s3sRJzl4b2"}],"key":"DUPAjvOysN"},{"type":"block","kind":"notebook-content","children":[{"type":"heading","depth":3,"position":{"start":{"line":1,"column":1},"end":{"line":1,"column":1}},"children":[{"type":"text","value":"8a. Inspecting dataset attributes","position":{"start":{"line":1,"column":1},"end":{"line":1,"column":1}},"key":"fewYARgQqc"}],"identifier":"id-8a-inspecting-dataset-attributes","label":"8a. Inspecting dataset attributes","html_id":"id-8a-inspecting-dataset-attributes","implicit":true,"key":"u0KSIMbEPJ"},{"type":"paragraph","position":{"start":{"line":3,"column":1},"end":{"line":3,"column":1}},"children":[{"type":"text","value":"Each GCOV dataset includes a set of attributes that describe how the data values should be interpreted. These attributes provide essential context such as units, valid value ranges, and how missing or invalid data are represented.","position":{"start":{"line":3,"column":1},"end":{"line":3,"column":1}},"key":"h6LMMWv34t"}],"key":"hxHc6BGD4F"},{"type":"paragraph","position":{"start":{"line":5,"column":1},"end":{"line":5,"column":1}},"children":[{"type":"text","value":"Before reading the dataset into memory or using it in analysis, we inspect these attributes to understand what the values might represent.","position":{"start":{"line":5,"column":1},"end":{"line":5,"column":1}},"key":"gvdlwmw3PU"}],"key":"KU9c5eaOFu"}],"key":"QffFn4d5RS"},{"type":"block","kind":"notebook-code","children":[{"type":"code","lang":"python","executable":true,"value":"#list all attributes attached to the HVHV dataset\nlist(hvhv.attrs)","key":"wFwtwVrskk"},{"type":"outputs","id":"znfMPtvesO7g4QC2Y32lP","children":[{"type":"output","jupyter_data":{"output_type":"execute_result","execution_count":11,"metadata":{},"data":{"text/plain":{"content":"['DIMENSION_LIST',\n '_FillValue',\n 'description',\n 'grid_mapping',\n 'long_name',\n 'max_value',\n 'mean_value',\n 'min_value',\n 'sample_stddev',\n 'units',\n 'valid_min']","content_type":"text/plain"}}},"children":[],"key":"edCDzKGd9j"}],"key":"kA5oFJUZc9"}],"key":"xZy96VX0fT"},{"type":"block","kind":"notebook-code","children":[{"type":"code","lang":"python","executable":true,"value":"#select key dataset attributes\n#before reading the dataset into memory, we inspect a small number of attributes that directly affect how the data should be handled in analysis and visualization\n\nprint(\"Fill value:\", hvhv.attrs.get(\"_FillValue\"))\nprint(\"Minimum valid value:\", hvhv.attrs.get(\"valid_min\"))","key":"I7M1OyR1vb"},{"type":"outputs","id":"Pi2yks2AmEaMCECLRqrwK","children":[{"type":"output","jupyter_data":{"name":"stdout","output_type":"stream","text":"Fill value: nan\nMinimum valid value: 0.0\n"},"children":[],"key":"YcXiWdZ0ry"}],"key":"zj50N6oiPN"}],"key":"pGhUXsMxO2"},{"type":"block","kind":"notebook-content","children":[{"type":"details","children":[{"type":"summary","children":[{"type":"text","value":"Output Explanation","position":{"start":{"line":1,"column":1},"end":{"line":1,"column":1}},"key":"B3EfLFa132"}],"key":"EPGx1WLJKW"},{"type":"list","ordered":false,"spread":false,"position":{"start":{"line":3,"column":1},"end":{"line":6,"column":1}},"children":[{"type":"listItem","spread":true,"position":{"start":{"line":3,"column":1},"end":{"line":4,"column":1}},"children":[{"type":"paragraph","position":{"start":{"line":3,"column":1},"end":{"line":3,"column":1}},"children":[{"type":"text","value":"The","position":{"start":{"line":3,"column":1},"end":{"line":3,"column":1}},"key":"WvkEGcjv6I"},{"type":"inlineCode","value":" _FillValue","position":{"start":{"line":3,"column":1},"end":{"line":3,"column":1}},"key":"aMrSpWEuzH"},{"type":"text","value":" attribute indicates how missing or invalid pixels are represented. In this dataset, missing values are stored as ","position":{"start":{"line":3,"column":1},"end":{"line":3,"column":1}},"key":"JJalj50GsO"},{"type":"inlineCode","value":"NaN","position":{"start":{"line":3,"column":1},"end":{"line":3,"column":1}},"key":"B6f6JlCqMs"},{"type":"text","value":", which are automatically handled by NumPy and plotting libraries.","position":{"start":{"line":3,"column":1},"end":{"line":3,"column":1}},"key":"Mw6KYmXx0Q"}],"key":"PYv6q5NTZe"}],"key":"igw6HqH3dJ"},{"type":"listItem","spread":true,"position":{"start":{"line":5,"column":1},"end":{"line":6,"column":1}},"children":[{"type":"paragraph","position":{"start":{"line":5,"column":1},"end":{"line":6,"column":1}},"children":[{"type":"text","value":"The ","position":{"start":{"line":5,"column":1},"end":{"line":5,"column":1}},"key":"vgbIYUT6rZ"},{"type":"inlineCode","value":"valid_min","position":{"start":{"line":5,"column":1},"end":{"line":5,"column":1}},"key":"wdmhI5rXVR"},{"type":"text","value":" attribute indicates that valid values are expected to be non-negative.\nIn this dataset, valid values are expected to be non-negative, which provides a simple sanity check when plotting or analyzing the data.","position":{"start":{"line":5,"column":1},"end":{"line":5,"column":1}},"key":"CHdLRk6RR1"}],"key":"bJvrAMg0u8"}],"key":"XgzpHmz8Cb"}],"key":"mZ5mUnRtnv"}],"key":"uN040JO31m"}],"key":"KKYvXArNih"},{"type":"block","kind":"notebook-content","children":[{"type":"thematicBreak","key":"c2vLriZF5S"}],"key":"IGTfgfgl2M"},{"type":"block","kind":"notebook-content","children":[{"type":"heading","depth":2,"position":{"start":{"line":2,"column":1},"end":{"line":2,"column":1}},"children":[{"type":"text","value":"9. Reading the dataset into memory","position":{"start":{"line":2,"column":1},"end":{"line":2,"column":1}},"key":"j5j0FPNnaA"}],"label":"hdf5-readmemory","identifier":"hdf5-readmemory","html_id":"hdf5-readmemory","key":"JcRhi8rSwy"},{"type":"paragraph","position":{"start":{"line":4,"column":1},"end":{"line":4,"column":1}},"children":[{"type":"text","value":"Up to this point, we have been working with an HDF5 dataset object, which provides access to metadata without loading the data values themselves. To perform calculations, visualization, or raster export, the dataset values must be explicitly read into memory.","position":{"start":{"line":4,"column":1},"end":{"line":4,"column":1}},"key":"bFIYYLxnKa"}],"key":"J5ANqx7wAo"},{"type":"paragraph","position":{"start":{"line":6,"column":1},"end":{"line":6,"column":1}},"children":[{"type":"text","value":"In this step, we load the ","position":{"start":{"line":6,"column":1},"end":{"line":6,"column":1}},"key":"XF7puMZ4EX"},{"type":"inlineCode","value":"HVHV","position":{"start":{"line":6,"column":1},"end":{"line":6,"column":1}},"key":"Kq2o4q6Icz"},{"type":"text","value":" dataset into a NumPy array.","position":{"start":{"line":6,"column":1},"end":{"line":6,"column":1}},"key":"dWnGnqJvtl"}],"key":"vCcjzMWNjB"}],"key":"CNf3a85ni7"},{"type":"block","kind":"notebook-code","children":[{"type":"code","lang":"python","executable":true,"value":"#read the full HVHV dataset into memory as a NumPy array\nhvhv_data = hvhv[()]\n\n#confirm the array shape\nhvhv_data.shape","key":"OHH9ZmFRbk"},{"type":"outputs","id":"v4b12TqbY3BviZrVCwWQJ","children":[{"type":"output","jupyter_data":{"output_type":"execute_result","execution_count":13,"metadata":{},"data":{"text/plain":{"content":"(16704, 17064)","content_type":"text/plain"}}},"children":[],"key":"AxmFsw29oO"}],"key":"fGmE1Lxndc"}],"key":"VWlanNk6vp"},{"type":"block","kind":"notebook-content","children":[{"type":"details","children":[{"type":"summary","children":[{"type":"text","value":"Output Explanation","position":{"start":{"line":1,"column":1},"end":{"line":1,"column":1}},"key":"FLxirvZQwK"}],"key":"a4qn33RGhM"},{"type":"list","ordered":false,"spread":false,"position":{"start":{"line":3,"column":1},"end":{"line":8,"column":1}},"children":[{"type":"listItem","spread":true,"position":{"start":{"line":3,"column":1},"end":{"line":4,"column":1}},"children":[{"type":"paragraph","position":{"start":{"line":3,"column":1},"end":{"line":3,"column":1}},"children":[{"type":"text","value":"hvhv_data is now a NumPy array containing the gridded covariance values.","position":{"start":{"line":3,"column":1},"end":{"line":3,"column":1}},"key":"kGeQkW29Pg"}],"key":"b66FU2QdGG"}],"key":"N0MDTNms7Y"},{"type":"listItem","spread":true,"position":{"start":{"line":5,"column":1},"end":{"line":6,"column":1}},"children":[{"type":"paragraph","position":{"start":{"line":5,"column":1},"end":{"line":5,"column":1}},"children":[{"type":"text","value":"The array shape matches the dimensions reported earlier by hvhv.shape.","position":{"start":{"line":5,"column":1},"end":{"line":5,"column":1}},"key":"pTndUtIuuA"}],"key":"FK4Ocrwqm8"}],"key":"BoIzMulclo"},{"type":"listItem","spread":true,"position":{"start":{"line":7,"column":1},"end":{"line":8,"column":1}},"children":[{"type":"paragraph","position":{"start":{"line":7,"column":1},"end":{"line":7,"column":1}},"children":[{"type":"text","value":"Missing values are represented as NaN, consistent with the _FillValue attribute.","position":{"start":{"line":7,"column":1},"end":{"line":7,"column":1}},"key":"gqlkOFSX81"}],"key":"O00AfhiHXo"}],"key":"XS844iqxCD"}],"key":"TNhIpLyBy3"},{"type":"paragraph","position":{"start":{"line":9,"column":1},"end":{"line":9,"column":1}},"children":[{"type":"text","value":"At this point, the GCOV raster values are available for direct analysis, visualization, or conversion to a standard raster format.","position":{"start":{"line":9,"column":1},"end":{"line":9,"column":1}},"key":"DI9w0I43tD"}],"key":"VbxWAzFWmo"}],"key":"omPQnR9hlc"}],"key":"y4FI3aJN6D"},{"type":"block","kind":"notebook-content","children":[{"type":"heading","depth":3,"position":{"start":{"line":1,"column":1},"end":{"line":1,"column":1}},"children":[{"type":"text","value":"9a. Reading the grid coordinate vectors","position":{"start":{"line":1,"column":1},"end":{"line":1,"column":1}},"key":"JJleSTSat2"}],"identifier":"id-9a-reading-the-grid-coordinate-vectors","label":"9a. Reading the grid coordinate vectors","html_id":"id-9a-reading-the-grid-coordinate-vectors","implicit":true,"key":"PjnXHwVx7l"},{"type":"paragraph","position":{"start":{"line":3,"column":1},"end":{"line":3,"column":1}},"children":[{"type":"text","value":"GCOV datasets are stored as gridded arrays, and the file provides coordinate datasets that define the spatial location of each pixel. The ","position":{"start":{"line":3,"column":1},"end":{"line":3,"column":1}},"key":"m0SZdLqp2X"},{"type":"inlineCode","value":"xCoordinates","position":{"start":{"line":3,"column":1},"end":{"line":3,"column":1}},"key":"tPjyYP7Kev"},{"type":"text","value":" and ","position":{"start":{"line":3,"column":1},"end":{"line":3,"column":1}},"key":"GmhdnWa7hk"},{"type":"inlineCode","value":"yCoordinates","position":{"start":{"line":3,"column":1},"end":{"line":3,"column":1}},"key":"eJuEvufzNX"},{"type":"text","value":" datasets provide the coordinate vectors for the grid, which are used to geolocate the raster.","position":{"start":{"line":3,"column":1},"end":{"line":3,"column":1}},"key":"POVgPcNNkW"}],"key":"zWpxdPML5m"}],"key":"FjzqEhLOjW"},{"type":"block","kind":"notebook-code","children":[{"type":"code","lang":"python","executable":true,"value":"#read the x and y coordinate vectors for the frequencyA grid\nx = f[\"science/LSAR/GCOV/grids/frequencyA/xCoordinates\"][:]\ny = f[\"science/LSAR/GCOV/grids/frequencyA/yCoordinates\"][:]\n\n#inspect coordinate ranges and lengths\nprint(f\"x range: {x.min():.1f} to {x.max():.1f}\")\nprint(f\"y range: {y.min():.1f} to {y.max():.1f}\")\nprint(f\"number of x coordinates (columns): {len(x)}\")\nprint(f\"number of y coordinates (rows): {len(y)}\")","key":"dGEZ4cfGLD"},{"type":"outputs","id":"kWN7bm0J-TI6fdO7b9BCb","children":[{"type":"output","jupyter_data":{"name":"stdout","output_type":"stream","text":"x range: 604090.0 to 945350.0\ny range: 1254250.0 to 1588310.0\nnumber of x coordinates (columns): 17064\nnumber of y coordinates (rows): 16704\n"},"children":[],"key":"wwOouLKe1C"}],"key":"x7rjsNAveK"}],"key":"JQuEEx2uQb"},{"type":"block","kind":"notebook-content","children":[{"type":"details","children":[{"type":"summary","children":[{"type":"text","value":"Output Explanation","position":{"start":{"line":1,"column":1},"end":{"line":1,"column":1}},"key":"S2Cf0Hjm5z"}],"key":"KBkJqk00gZ"},{"type":"list","ordered":false,"spread":false,"position":{"start":{"line":2,"column":1},"end":{"line":6,"column":1}},"children":[{"type":"listItem","spread":true,"position":{"start":{"line":2,"column":1},"end":{"line":3,"column":1}},"children":[{"type":"paragraph","position":{"start":{"line":2,"column":1},"end":{"line":2,"column":1}},"children":[{"type":"inlineCode","value":"x","position":{"start":{"line":2,"column":1},"end":{"line":2,"column":1}},"key":"MG9UOWivqd"},{"type":"text","value":" and ","position":{"start":{"line":2,"column":1},"end":{"line":2,"column":1}},"key":"bZaQZEoyWE"},{"type":"inlineCode","value":"y","position":{"start":{"line":2,"column":1},"end":{"line":2,"column":1}},"key":"GUPDgupnnV"},{"type":"text","value":" are one-dimensional coordinate vectors that define the grid in the product’s projected coordinate system.","position":{"start":{"line":2,"column":1},"end":{"line":2,"column":1}},"key":"hIAogcr8Yr"}],"key":"XCzaSfKzyc"}],"key":"XmnRMWw0ZI"},{"type":"listItem","spread":true,"position":{"start":{"line":4,"column":1},"end":{"line":5,"column":1}},"children":[{"type":"paragraph","position":{"start":{"line":4,"column":1},"end":{"line":4,"column":1}},"children":[{"type":"text","value":"The length of ","position":{"start":{"line":4,"column":1},"end":{"line":4,"column":1}},"key":"YNecOfnqAG"},{"type":"inlineCode","value":"x","position":{"start":{"line":4,"column":1},"end":{"line":4,"column":1}},"key":"L7JEtB2tJz"},{"type":"text","value":" corresponds to the number of raster columns, and the length of ","position":{"start":{"line":4,"column":1},"end":{"line":4,"column":1}},"key":"cbOobqrBLn"},{"type":"inlineCode","value":"y","position":{"start":{"line":4,"column":1},"end":{"line":4,"column":1}},"key":"bucsOvXWPA"},{"type":"text","value":" corresponds to the number of raster rows. These should match the dimensions of ","position":{"start":{"line":4,"column":1},"end":{"line":4,"column":1}},"key":"jO0sbPuA58"},{"type":"inlineCode","value":"hvhv_data","position":{"start":{"line":4,"column":1},"end":{"line":4,"column":1}},"key":"DCt2NVwYPw"},{"type":"text","value":".","position":{"start":{"line":4,"column":1},"end":{"line":4,"column":1}},"key":"EF228SpXsr"}],"key":"pAh9d8Yqv5"}],"key":"yOm3o1lWFg"},{"type":"listItem","spread":true,"position":{"start":{"line":6,"column":1},"end":{"line":6,"column":1}},"children":[{"type":"paragraph","position":{"start":{"line":6,"column":1},"end":{"line":6,"column":1}},"children":[{"type":"text","value":"The minimum and maximum values of ","position":{"start":{"line":6,"column":1},"end":{"line":6,"column":1}},"key":"apwU4dR2Xs"},{"type":"inlineCode","value":"x","position":{"start":{"line":6,"column":1},"end":{"line":6,"column":1}},"key":"FiqAlonxP3"},{"type":"text","value":" and ","position":{"start":{"line":6,"column":1},"end":{"line":6,"column":1}},"key":"t4v8vA8CnO"},{"type":"inlineCode","value":"y","position":{"start":{"line":6,"column":1},"end":{"line":6,"column":1}},"key":"M08dxhidGv"},{"type":"text","value":" define the spatial extent of the GCOV grid.","position":{"start":{"line":6,"column":1},"end":{"line":6,"column":1}},"key":"fJplVKiTJA"}],"key":"XDnFUzoRcy"}],"key":"jUia5431LE"}],"key":"WwmYh0zhFO"}],"key":"w6ZAcyvFKt"}],"key":"D7nuVPPBR8"},{"type":"block","kind":"notebook-content","children":[{"type":"heading","depth":3,"position":{"start":{"line":1,"column":1},"end":{"line":1,"column":1}},"children":[{"type":"text","value":"9b. Reading grid spacing","position":{"start":{"line":1,"column":1},"end":{"line":1,"column":1}},"key":"gjZpcXoEiZ"}],"identifier":"id-9b-reading-grid-spacing","label":"9b. Reading grid spacing","html_id":"id-9b-reading-grid-spacing","implicit":true,"key":"MbPv3vou9W"},{"type":"paragraph","position":{"start":{"line":3,"column":1},"end":{"line":3,"column":1}},"children":[{"type":"text","value":"The ","position":{"start":{"line":3,"column":1},"end":{"line":3,"column":1}},"key":"Sm6mKGV9rd"},{"type":"inlineCode","value":"xCoordinates","position":{"start":{"line":3,"column":1},"end":{"line":3,"column":1}},"key":"cgKj760jXk"},{"type":"text","value":" and ","position":{"start":{"line":3,"column":1},"end":{"line":3,"column":1}},"key":"RGum3y1Do8"},{"type":"inlineCode","value":"yCoordinates","position":{"start":{"line":3,"column":1},"end":{"line":3,"column":1}},"key":"Djw4jNGY2l"},{"type":"text","value":" vectors define the grid location, but we also need the spacing between pixels. GCOV products provide ","position":{"start":{"line":3,"column":1},"end":{"line":3,"column":1}},"key":"krBiGwTDet"},{"type":"inlineCode","value":"xCoordinateSpacing","position":{"start":{"line":3,"column":1},"end":{"line":3,"column":1}},"key":"Khdqg2G85u"},{"type":"text","value":" and ","position":{"start":{"line":3,"column":1},"end":{"line":3,"column":1}},"key":"wfyOW9LOeS"},{"type":"inlineCode","value":"yCoordinateSpacing","position":{"start":{"line":3,"column":1},"end":{"line":3,"column":1}},"key":"ZJyQ32VxAP"},{"type":"text","value":", which describe the pixel size in the projected coordinate system. These values are useful for confirming resolution and for constructing a georeferencing transform during raster export.","position":{"start":{"line":3,"column":1},"end":{"line":3,"column":1}},"key":"SD9Go8lCGb"}],"key":"BSDQbc6huS"}],"key":"xXRIVQ2N04"},{"type":"block","kind":"notebook-code","children":[{"type":"code","lang":"python","executable":true,"value":"#read the grid spacing (pixel size) for the frequencyA grid\ndx = f[\"science/LSAR/GCOV/grids/frequencyA/xCoordinateSpacing\"][()]\ndy = f[\"science/LSAR/GCOV/grids/frequencyA/yCoordinateSpacing\"][()]\n\n#print\nprint(f\"x spacing (dx): {float(dx)}\")\nprint(f\"y spacing (dy): {float(dy)}\")","key":"NeaPE3bhQV"},{"type":"outputs","id":"GbTM4Kwn9ljtNpXQTlrRx","children":[{"type":"output","jupyter_data":{"name":"stdout","output_type":"stream","text":"x spacing (dx): 20.0\ny spacing (dy): -20.0\n"},"children":[],"key":"oBQbA2CAjH"}],"key":"GXoMFwUNrd"}],"key":"gaFelx9a7N"},{"type":"block","kind":"notebook-content","children":[{"type":"details","children":[{"type":"summary","children":[{"type":"text","value":"Output Explanation","position":{"start":{"line":1,"column":1},"end":{"line":1,"column":1}},"key":"MhLulYZObU"}],"key":"z2Xf4u1P59"},{"type":"list","ordered":false,"spread":false,"position":{"start":{"line":3,"column":1},"end":{"line":8,"column":1}},"children":[{"type":"listItem","spread":true,"position":{"start":{"line":3,"column":1},"end":{"line":4,"column":1}},"children":[{"type":"paragraph","position":{"start":{"line":3,"column":1},"end":{"line":3,"column":1}},"children":[{"type":"text","value":"The grid spacing in the x-direction (","position":{"start":{"line":3,"column":1},"end":{"line":3,"column":1}},"key":"OkzFq2bwyD"},{"type":"inlineCode","value":"dx","position":{"start":{"line":3,"column":1},"end":{"line":3,"column":1}},"key":"I1LXmKK7Ge"},{"type":"text","value":") is 20 meters, indicating a pixel width of 20 m in the projected coordinate system.","position":{"start":{"line":3,"column":1},"end":{"line":3,"column":1}},"key":"Cn2NzzMLTb"}],"key":"CKfWoZ9VS7"}],"key":"ucGCP1V6IH"},{"type":"listItem","spread":true,"position":{"start":{"line":5,"column":1},"end":{"line":6,"column":1}},"children":[{"type":"paragraph","position":{"start":{"line":5,"column":1},"end":{"line":5,"column":1}},"children":[{"type":"text","value":"The grid spacing in the y-direction (","position":{"start":{"line":5,"column":1},"end":{"line":5,"column":1}},"key":"VCWuIqhr5C"},{"type":"inlineCode","value":"dy","position":{"start":{"line":5,"column":1},"end":{"line":5,"column":1}},"key":"zYkfh4WVKk"},{"type":"text","value":") is −20 meters. The negative sign indicates that y-coordinates decrease from north to south, which is a common convention for raster grids.","position":{"start":{"line":5,"column":1},"end":{"line":5,"column":1}},"key":"bhghbe5TEV"}],"key":"KSKyQUWhmV"}],"key":"co1RJbjsmw"},{"type":"listItem","spread":true,"position":{"start":{"line":7,"column":1},"end":{"line":8,"column":1}},"children":[{"type":"paragraph","position":{"start":{"line":7,"column":1},"end":{"line":7,"column":1}},"children":[{"type":"text","value":"Together, these values indicate that the GCOV data are provided on a 20 m × 20 m grid.","position":{"start":{"line":7,"column":1},"end":{"line":7,"column":1}},"key":"cwE14ZBq15"}],"key":"zWcQZK5owA"}],"key":"KsKBhIE6uL"}],"key":"Ya1xyIWUJg"},{"type":"paragraph","position":{"start":{"line":9,"column":1},"end":{"line":9,"column":1}},"children":[{"type":"text","value":"This spacing information, combined with the coordinate vectors, is used to construct a georeferencing transform when converting the GCOV dataset to a standard raster format.","position":{"start":{"line":9,"column":1},"end":{"line":9,"column":1}},"key":"WKBuTUAYcn"}],"key":"QO0aGEP7dI"}],"key":"wiYYr8kXUT"}],"key":"XY1yy5OiPM"},{"type":"block","kind":"notebook-content","children":[{"type":"heading","depth":3,"position":{"start":{"line":1,"column":1},"end":{"line":1,"column":1}},"children":[{"type":"text","value":"9c. Reading projection information","position":{"start":{"line":1,"column":1},"end":{"line":1,"column":1}},"key":"pprDFH3x8j"}],"identifier":"id-9c-reading-projection-information","label":"9c. Reading projection information","html_id":"id-9c-reading-projection-information","implicit":true,"key":"UalcXwewFf"},{"type":"paragraph","position":{"start":{"line":3,"column":1},"end":{"line":3,"column":1}},"children":[{"type":"text","value":"The GCOV grid is defined in a projected coordinate system. To correctly interpret the coordinate values and export a georeferenced raster, we need to identify the projection used by the grid.","position":{"start":{"line":3,"column":1},"end":{"line":3,"column":1}},"key":"Lj9iMTNv7H"}],"key":"yarBDoMz69"},{"type":"paragraph","position":{"start":{"line":5,"column":1},"end":{"line":5,"column":1}},"children":[{"type":"text","value":"GCOV products store projection information within each frequency group.","position":{"start":{"line":5,"column":1},"end":{"line":5,"column":1}},"key":"evIaxBtnbC"}],"key":"UvjkEU1ASr"}],"key":"Wdh1InENVw"},{"type":"block","kind":"notebook-code","children":[{"type":"code","lang":"python","executable":true,"value":"#read the projection information for the frequencyA grid\nprojection = f[\"science/LSAR/GCOV/grids/frequencyA/projection\"][()]\n\nprojection","key":"LNovmOeSYE"},{"type":"outputs","id":"X5HG6mTbngLmfY2Sk-URY","children":[{"type":"output","jupyter_data":{"output_type":"execute_result","execution_count":16,"metadata":{},"data":{"text/plain":{"content":"np.uint32(32637)","content_type":"text/plain"}}},"children":[],"key":"u5ZLxtk2Ka"}],"key":"PTu7lbEOYa"}],"key":"R7zVx3jkJS"},{"type":"block","kind":"notebook-content","children":[{"type":"details","children":[{"type":"summary","children":[{"type":"text","value":"Output Explanation","position":{"start":{"line":1,"column":1},"end":{"line":1,"column":1}},"key":"layjwT5c4q"}],"key":"Xdv0fbDzTX"},{"type":"list","ordered":false,"spread":false,"position":{"start":{"line":3,"column":1},"end":{"line":8,"column":1}},"children":[{"type":"listItem","spread":true,"position":{"start":{"line":3,"column":1},"end":{"line":4,"column":1}},"children":[{"type":"paragraph","position":{"start":{"line":3,"column":1},"end":{"line":3,"column":1}},"children":[{"type":"text","value":"The projection value is 32637, stored as an unsigned integer (","position":{"start":{"line":3,"column":1},"end":{"line":3,"column":1}},"key":"iZqNnenSYf"},{"type":"inlineCode","value":"np.uint32","position":{"start":{"line":3,"column":1},"end":{"line":3,"column":1}},"key":"zz1hOjbvWC"},{"type":"text","value":").","position":{"start":{"line":3,"column":1},"end":{"line":3,"column":1}},"key":"jJ7CDq5gNy"}],"key":"uQiU3KPWsM"}],"key":"lyt4qsn6Ad"},{"type":"listItem","spread":true,"position":{"start":{"line":5,"column":1},"end":{"line":6,"column":1}},"children":[{"type":"paragraph","position":{"start":{"line":5,"column":1},"end":{"line":5,"column":1}},"children":[{"type":"text","value":"This is an EPSG code, meaning the GCOV grid uses the coordinate reference system EPSG:32637.","position":{"start":{"line":5,"column":1},"end":{"line":5,"column":1}},"key":"iqjuEs4GN5"}],"key":"u2bA8UdSn3"}],"key":"v8wqlLBFMG"},{"type":"listItem","spread":true,"position":{"start":{"line":7,"column":1},"end":{"line":8,"column":1}},"children":[{"type":"paragraph","position":{"start":{"line":7,"column":1},"end":{"line":7,"column":1}},"children":[{"type":"text","value":"The ","position":{"start":{"line":7,"column":1},"end":{"line":7,"column":1}},"key":"pxwLOEgRev"},{"type":"inlineCode","value":"xCoordinates","position":{"start":{"line":7,"column":1},"end":{"line":7,"column":1}},"key":"AQcrPC02al"},{"type":"text","value":" and ","position":{"start":{"line":7,"column":1},"end":{"line":7,"column":1}},"key":"FjqCdApm6w"},{"type":"inlineCode","value":"yCoordinates","position":{"start":{"line":7,"column":1},"end":{"line":7,"column":1}},"key":"c9sOY1ifKB"},{"type":"text","value":" values are therefore in meters in this projected CRS.","position":{"start":{"line":7,"column":1},"end":{"line":7,"column":1}},"key":"L72xfDugYM"}],"key":"Ut3L868Z1b"}],"key":"mNuiY5RjiI"}],"key":"mCY1rsmuqc"},{"type":"paragraph","position":{"start":{"line":9,"column":1},"end":{"line":9,"column":1}},"children":[{"type":"text","value":"With the CRS identified, we can now create a georeferencing transform and export the ","position":{"start":{"line":9,"column":1},"end":{"line":9,"column":1}},"key":"uc0XQ5CW9b"},{"type":"inlineCode","value":"HVHV","position":{"start":{"line":9,"column":1},"end":{"line":9,"column":1}},"key":"GB1xuKNNb7"},{"type":"text","value":" dataset to a GeoTIFF with a valid CRS.","position":{"start":{"line":9,"column":1},"end":{"line":9,"column":1}},"key":"aeiO5ibbpG"}],"key":"BQqPJW0fmo"}],"key":"Tzr7i1ifPE"}],"key":"QllcjyLmX2"},{"type":"block","kind":"notebook-content","children":[{"type":"thematicBreak","key":"n1Wsa9hTN3"}],"key":"cjw76rao3v"},{"type":"block","kind":"notebook-content","children":[{"type":"heading","depth":2,"position":{"start":{"line":2,"column":1},"end":{"line":2,"column":1}},"children":[{"type":"text","value":"10. Build a raster transform and export to GeoTIFF","position":{"start":{"line":2,"column":1},"end":{"line":2,"column":1}},"key":"AOjQOitKzk"}],"label":"hdf5-geotiff","identifier":"hdf5-geotiff","html_id":"hdf5-geotiff","key":"u7MTQSg1kH"},{"type":"paragraph","position":{"start":{"line":4,"column":1},"end":{"line":4,"column":1}},"children":[{"type":"text","value":"Now we combine:","position":{"start":{"line":4,"column":1},"end":{"line":4,"column":1}},"key":"HsNrxiDPkH"}],"key":"yXAshbNMzy"},{"type":"list","ordered":false,"spread":false,"position":{"start":{"line":5,"column":1},"end":{"line":8,"column":1}},"children":[{"type":"listItem","spread":true,"position":{"start":{"line":5,"column":1},"end":{"line":5,"column":1}},"children":[{"type":"paragraph","children":[{"type":"text","value":"coordinate vectors (","position":{"start":{"line":5,"column":1},"end":{"line":5,"column":1}},"key":"M7Ht72W2CM"},{"type":"inlineCode","value":"x","position":{"start":{"line":5,"column":1},"end":{"line":5,"column":1}},"key":"FDJJDgb48o"},{"type":"text","value":", ","position":{"start":{"line":5,"column":1},"end":{"line":5,"column":1}},"key":"KSxZwpV9fa"},{"type":"inlineCode","value":"y","position":{"start":{"line":5,"column":1},"end":{"line":5,"column":1}},"key":"X2IC2QiXoh"},{"type":"text","value":")","position":{"start":{"line":5,"column":1},"end":{"line":5,"column":1}},"key":"EZgW0hnHNR"}],"key":"oyesB5pHJT"}],"key":"q4IERFuEXo"},{"type":"listItem","spread":true,"position":{"start":{"line":6,"column":1},"end":{"line":6,"column":1}},"children":[{"type":"paragraph","children":[{"type":"text","value":"pixel spacing (","position":{"start":{"line":6,"column":1},"end":{"line":6,"column":1}},"key":"fahVHp5Bn1"},{"type":"inlineCode","value":"dx","position":{"start":{"line":6,"column":1},"end":{"line":6,"column":1}},"key":"dPNuIJTiL1"},{"type":"text","value":", ","position":{"start":{"line":6,"column":1},"end":{"line":6,"column":1}},"key":"UfUBY2BY3t"},{"type":"inlineCode","value":"dy","position":{"start":{"line":6,"column":1},"end":{"line":6,"column":1}},"key":"AFnFn099q8"},{"type":"text","value":")","position":{"start":{"line":6,"column":1},"end":{"line":6,"column":1}},"key":"gelSUDdySA"}],"key":"vO8F5ITaou"}],"key":"ABXoqTC7fy"},{"type":"listItem","spread":true,"position":{"start":{"line":7,"column":1},"end":{"line":8,"column":1}},"children":[{"type":"paragraph","children":[{"type":"text","value":"CRS (EPSG:32637)","position":{"start":{"line":7,"column":1},"end":{"line":7,"column":1}},"key":"rxF3Qi25vn"}],"key":"LlzfBDc9ym"}],"key":"AqzbRKRbsl"}],"key":"oDegId4WmO"},{"type":"paragraph","position":{"start":{"line":9,"column":1},"end":{"line":9,"column":1}},"children":[{"type":"text","value":"to export a properly georeferenced raster.","position":{"start":{"line":9,"column":1},"end":{"line":9,"column":1}},"key":"anVHtLf4J8"}],"key":"TJUZrifEFc"}],"key":"rKtnVcbtLa"},{"type":"block","kind":"notebook-code","children":[{"type":"code","lang":"python","executable":true,"value":"import numpy as np\nimport rasterio\nfrom rasterio.transform import from_origin\n\n#convert the projection value into a CRS string for rasterio \ncrs = f\"EPSG:{int(projection)}\"\n\n#build pixel footprint\n#x.min() gives the left edge of the raster\n#y.max() gives the top edge of the raster\n#dx is the pixel width\n#abs(dy) is the pixel height (use absolute value to ensure positive values)\ntransform = from_origin(\n    x.min(),          #x-coordinate of the upper-left corner\n    y.max(),          #y-coordinate of the upper-left corner\n    float(dx),        #pixel width (meters)\n    float(abs(dy))    #pixel height (meters)\n)\n\n#name of the output GeoTIFF file\nout_tif = data_dir / \"GCOV_frequencyA_HVHV.tif\"\n\n#open a new GeoTIFF file \nwith rasterio.open(\n    out_tif,\n    \"w\",                      #write mode\n    driver=\"GTiff\",           #output file format\n    height=hvhv_data.shape[0],#number of rows\n    width=hvhv_data.shape[1], #number of columns\n    count=1,                  #single-band raster\n    dtype=hvhv_data.dtype,    #data type matches the NumPy array\n    crs=crs,                  #coordinate reference system\n    transform=transform,      #georeferencing information\n    nodata=np.nan,            #missing values stored as NaNs\n) as dst:\n    #write the HVHV data array to band 1 of the GeoTIFF\n    dst.write(hvhv_data, 1)\n\n#print the output filename for confirmation of file creation\nout_tif\n","key":"n7drpe1frD"},{"type":"outputs","id":"tAWHQjoZrNA8p_6Hcs_eb","children":[{"type":"output","jupyter_data":{"output_type":"execute_result","execution_count":17,"metadata":{},"data":{"text/plain":{"content":"PosixPath('/home/jovyan/GCOV_data/GCOV_frequencyA_HVHV.tif')","content_type":"text/plain"}}},"children":[],"key":"UlpVN2JxEB"}],"key":"CczinXUZ3L"}],"key":"mO3D1uTIWT"},{"type":"block","kind":"notebook-code","children":[{"type":"code","lang":"python","executable":true,"value":"#quality check\nwith rasterio.open(out_tif) as src:\n    print(\"CRS:\", src.crs)\n    print(\"Resolution:\", src.res)\n    print(\"Bounds:\", src.bounds)\n","key":"gpfDXCxNDJ"},{"type":"outputs","id":"MasnhIOFhRJs7D_Bn-z7j","children":[{"type":"output","jupyter_data":{"name":"stdout","output_type":"stream","text":"CRS: EPSG:32637\nResolution: (20.0, 20.0)\nBounds: BoundingBox(left=604090.0, bottom=1254230.0, right=945370.0, top=1588310.0)\n"},"children":[],"key":"OByrD750GI"}],"key":"nOlQ8N8OsB"}],"key":"reVqBnISo7"},{"type":"block","kind":"notebook-content","children":[{"type":"thematicBreak","key":"VRjGm5zhTj"}],"key":"qBdLiz7WMS"},{"type":"block","kind":"notebook-content","children":[{"type":"heading","depth":2,"position":{"start":{"line":2,"column":1},"end":{"line":2,"column":1}},"children":[{"type":"text","value":"11. Summary","position":{"start":{"line":2,"column":1},"end":{"line":2,"column":1}},"key":"v5JsVQHU6U"}],"label":"HDF5-summary","identifier":"hdf5-summary","html_id":"hdf5-summary","key":"pFziq8izRb"},{"type":"paragraph","position":{"start":{"line":3,"column":1},"end":{"line":3,"column":1}},"children":[{"type":"text","value":"You have now opened and navigated an HDF5 file, saved it to memory, and exported a layer as a GeoTIFF.","position":{"start":{"line":3,"column":1},"end":{"line":3,"column":1}},"key":"JzOfbuaIIy"}],"key":"MUAMrx4Qox"},{"type":"thematicBreak","key":"m6ouG9O51c"}],"key":"n3uWqYUSSX"},{"type":"block","kind":"notebook-content","children":[{"type":"heading","depth":2,"position":{"start":{"line":2,"column":1},"end":{"line":2,"column":1}},"children":[{"type":"text","value":"12. Resources and references","position":{"start":{"line":2,"column":1},"end":{"line":2,"column":1}},"key":"NPQUcS1amK"}],"label":"hdf5-resources","identifier":"hdf5-resources","html_id":"hdf5-resources","key":"DORDAP0Ogr"},{"type":"list","ordered":false,"spread":false,"position":{"start":{"line":3,"column":1},"end":{"line":5,"column":1}},"children":[{"type":"listItem","spread":true,"position":{"start":{"line":3,"column":1},"end":{"line":3,"column":1}},"children":[{"type":"paragraph","children":[{"type":"link","url":"https://d1mv8zhcvry6x4.cloudfront.net/s3-7fdfbcb0ce308dc58d08f97acb1f0590/sds-n-cumulus-prod-nisar-sample-data.s3.us-west-2.amazonaws.com/DOCS/NISAR_D-102274_RevE_NASA_SDS_Product_Specification_L2_GCOV_Nov8_2024_w-sigs.pdf?A-userid=None&Expires=1772497215&Signature=FTbel0AsOFTbJljWTPumbhEkBWUgv3DHAeO4cQ7lYx-nwsgUycC3YDjIHnT--sFwvrnG9I8g2-~InboeRqWavjXbM1pfl-l1Ek9JNqMm0tkFn9Zpraa3oGdRX5671OFfspQF2eH04XYzBAiFCuun1CnAYoYrfQ5Y9u~7Y4IxqvV5wX8vZA3fZBDqX3jh7pibEe-2ZAAS9a-O0K~IsxGEV7F9xzu3Fd3VYe4~emOsF79b8kv1nPlPLFPrOXgNX5ftggAu1jUna2A63DI7CWRkTIXo4GvAebhMeubss66iSgpPortVQBr9zt2qGJ6xk~ygfMEt5Vgk4Dl3NQs1Aocwzw__&Key-Pair-Id=K1MF06CKIT7LR7","position":{"start":{"line":3,"column":1},"end":{"line":3,"column":1}},"children":[{"type":"text","value":"GCOV Specifications","position":{"start":{"line":3,"column":1},"end":{"line":3,"column":1}},"key":"KplXl3souc"}],"urlSource":"https://d1mv8zhcvry6x4.cloudfront.net/s3-7fdfbcb0ce308dc58d08f97acb1f0590/sds-n-cumulus-prod-nisar-sample-data.s3.us-west-2.amazonaws.com/DOCS/NISAR_D-102274_RevE_NASA_SDS_Product_Specification_L2_GCOV_Nov8_2024_w-sigs.pdf?A-userid=None&Expires=1772497215&Signature=FTbel0AsOFTbJljWTPumbhEkBWUgv3DHAeO4cQ7lYx-nwsgUycC3YDjIHnT--sFwvrnG9I8g2-~InboeRqWavjXbM1pfl-l1Ek9JNqMm0tkFn9Zpraa3oGdRX5671OFfspQF2eH04XYzBAiFCuun1CnAYoYrfQ5Y9u~7Y4IxqvV5wX8vZA3fZBDqX3jh7pibEe-2ZAAS9a-O0K~IsxGEV7F9xzu3Fd3VYe4~emOsF79b8kv1nPlPLFPrOXgNX5ftggAu1jUna2A63DI7CWRkTIXo4GvAebhMeubss66iSgpPortVQBr9zt2qGJ6xk~ygfMEt5Vgk4Dl3NQs1Aocwzw__&Key-Pair-Id=K1MF06CKIT7LR7","key":"nbkFHgkkd0"}],"key":"MPdHiO98X3"}],"key":"RiUCajWQFt"},{"type":"listItem","spread":true,"position":{"start":{"line":4,"column":1},"end":{"line":5,"column":1}},"children":[{"type":"paragraph","children":[{"type":"link","url":"https://support.hdfgroup.org/documentation/","position":{"start":{"line":4,"column":1},"end":{"line":4,"column":1}},"children":[{"type":"text","value":"HDF5 Documentation","position":{"start":{"line":4,"column":1},"end":{"line":4,"column":1}},"key":"nswC70prY5"}],"urlSource":"https://support.hdfgroup.org/documentation/","key":"BA5SoAEQi4"}],"key":"ealhFRDYkt"}],"key":"UVoA80kbQo"}],"key":"oh08wkJ0iM"},{"type":"paragraph","position":{"start":{"line":6,"column":1},"end":{"line":6,"column":1}},"children":[{"type":"strong","position":{"start":{"line":6,"column":1},"end":{"line":6,"column":1}},"children":[{"type":"text","value":"Authors:","position":{"start":{"line":6,"column":1},"end":{"line":6,"column":1}},"key":"MPHU3MxqAv"}],"key":"Fzh23MVtLy"},{"type":"text","value":" Julia White, Alex Lewandowski","position":{"start":{"line":6,"column":1},"end":{"line":6,"column":1}},"key":"ii2yErYhYN"}],"key":"xFeukIGUMm"}],"key":"nSG2oXe6mA"},{"type":"block","kind":"notebook-content","children":[{"type":"thematicBreak","key":"Vky622WMP1"}],"key":"zmq6ro61Dm"}],"key":"wznrvA4dEs"},"references":{"cite":{"order":[],"data":{}}},"footer":{"navigation":{"prev":{"title":"Search, Download, and Stream NISAR GCOV Data with earthaccess","url":"/notebooks/search-nisar-gcov-earthaccess","group":"Data Access"},"next":{"title":"NISAR Pixel Conversion","url":"/notebooks/nisar-pixel-conversion","group":"Data Access"}}},"domain":"http://localhost:3000"}