{"version":3,"kind":"Notebook","sha256":"03b102238b48263b61d4feeee7840f1825a441bc9d3918f690de939c12e2992d","slug":"notebooks.software-environment-docker","location":"/notebooks/software_environment_docker.ipynb","dependencies":[],"frontmatter":{"title":"Install Required Software or Run a Docker Image","content_includes_title":false,"kernelspec":{"name":"conda-base-py","display_name":"base [conda env:base] *","language":"python"},"authors":[{"nameParsed":{"literal":"The Alaska Satellite Facility","given":"The Alaska Satellite","family":"Facility"},"name":"The Alaska Satellite Facility","id":"contributors-myst-generated-uid-0"}],"open_access":true,"license":{"content":{"id":"BSD-3-Clause","url":"https://opensource.org/licenses/BSD-3-Clause","name":"BSD 3-Clause \"New\" or \"Revised\" License","free":true,"osi":true}},"github":"https://github.com/ASFOpenSARlab/NISAR_GCOV_Cookbook","copyright":"2025","affiliations":[{"id":"UAF","name":"University of Alaska Fairbanks","department":"Geophysical Institute","url":"https://www.gi.alaska.edu/"},{"id":"ASF","name":"Alaska Satellite Facility","url":"https://asf.alaska.edu/"}],"numbering":{"title":{"offset":1}},"source_url":"https://github.com/ASFOpenSARlab/NISAR_GCOV_Cookbook/blob/main/notebooks/software_environment_docker.ipynb","edit_url":"https://github.com/ASFOpenSARlab/NISAR_GCOV_Cookbook/edit/main/notebooks/software_environment_docker.ipynb","exports":[{"format":"ipynb","filename":"software_environment_docker.ipynb","url":"/NISAR_GCOV_Cookbook/_preview/14/build/software_environment-ac9985ee9b28c06810c959994232847d.ipynb"}]},"widgets":{},"mdast":{"type":"root","children":[{"type":"block","kind":"notebook-content","children":[{"type":"break","key":"YGqCHtPRDt"},{"type":"paragraph","position":{"start":{"line":5,"column":1},"end":{"line":5,"column":1}},"children":[{"type":"text","value":"This notebook installs the Pixi software environment required to run the other notebooks in the NISAR GCOV Cookbook.","position":{"start":{"line":5,"column":1},"end":{"line":5,"column":1}},"key":"KNcbg6EuHR"}],"key":"DT8Fe67uql"},{"type":"thematicBreak","key":"v2aqkMB9gL"},{"type":"heading","depth":2,"position":{"start":{"line":9,"column":1},"end":{"line":9,"column":1}},"children":[{"type":"text","value":"Overview","position":{"start":{"line":9,"column":1},"end":{"line":9,"column":1}},"key":"YX9hWjDroE"}],"identifier":"overview","label":"Overview","html_id":"overview","implicit":true,"key":"WvH5JPQ3IZ"},{"type":"list","ordered":true,"start":1,"spread":false,"position":{"start":{"line":11,"column":1},"end":{"line":16,"column":1}},"children":[{"type":"listItem","spread":true,"position":{"start":{"line":11,"column":1},"end":{"line":11,"column":1}},"children":[{"type":"paragraph","children":[{"type":"crossReference","position":{"start":{"line":11,"column":1},"end":{"line":11,"column":1}},"children":[{"type":"text","value":"Prerequisites","position":{"start":{"line":11,"column":1},"end":{"line":11,"column":1}},"key":"HY2TDo6m0d"}],"identifier":"env-prereqs","label":"env-prereqs","kind":"heading","template":"{name}","resolved":true,"html_id":"env-prereqs","key":"GjvcgCVsWk"}],"key":"TrpfFBCGgQ"}],"key":"Gj1Ah0k5pW"},{"type":"listItem","spread":true,"position":{"start":{"line":12,"column":1},"end":{"line":12,"column":1}},"children":[{"type":"paragraph","children":[{"type":"crossReference","position":{"start":{"line":12,"column":1},"end":{"line":12,"column":1}},"children":[{"type":"text","value":"(Option 1) Install the environment with the Pixi pacakage manager","position":{"start":{"line":12,"column":1},"end":{"line":12,"column":1}},"key":"fWkz8z8qOY"}],"identifier":"env-pixi","label":"env-pixi","kind":"heading","template":"{name}","resolved":true,"html_id":"env-pixi","key":"lYuH8G2yw2"}],"key":"BDLp01xooO"}],"key":"UEhPd22ORR"},{"type":"listItem","spread":true,"position":{"start":{"line":13,"column":1},"end":{"line":13,"column":1}},"children":[{"type":"paragraph","children":[{"type":"crossReference","position":{"start":{"line":13,"column":1},"end":{"line":13,"column":1}},"children":[{"type":"text","value":"(Option 2) Run a Docker Image with the software environment already installed","position":{"start":{"line":13,"column":1},"end":{"line":13,"column":1}},"key":"zu2y2Vnedp"}],"identifier":"env-docker","label":"env-docker","kind":"heading","template":"{name}","resolved":true,"html_id":"env-docker","key":"tfiC9gmgL7"}],"key":"W5jKvo4ENy"}],"key":"IUzogXNx8v"},{"type":"listItem","spread":true,"position":{"start":{"line":14,"column":1},"end":{"line":14,"column":1}},"children":[{"type":"paragraph","children":[{"type":"crossReference","position":{"start":{"line":14,"column":1},"end":{"line":14,"column":1}},"children":[{"type":"text","value":"Summary","position":{"start":{"line":14,"column":1},"end":{"line":14,"column":1}},"key":"IaBLDDt6cb"}],"identifier":"env-summary","label":"env-summary","kind":"heading","template":"{name}","resolved":true,"html_id":"env-summary","key":"bxIMDUF4Tw"}],"key":"s9D0SKhT0f"}],"key":"RCv3DnaFXE"},{"type":"listItem","spread":true,"position":{"start":{"line":15,"column":1},"end":{"line":16,"column":1}},"children":[{"type":"paragraph","children":[{"type":"crossReference","position":{"start":{"line":15,"column":1},"end":{"line":15,"column":1}},"children":[{"type":"text","value":"Resources and references","position":{"start":{"line":15,"column":1},"end":{"line":15,"column":1}},"key":"C3kuysRgVy"}],"identifier":"env-resources","label":"env-resources","kind":"heading","template":"{name}","resolved":true,"html_id":"env-resources","key":"xHFsl6ls0P"}],"key":"ZSAbKcT3ln"}],"key":"P1OuB0NDWe"}],"key":"I7sBeSg79i"},{"type":"thematicBreak","key":"TLBSfIZzv0"},{"type":"heading","depth":2,"position":{"start":{"line":20,"column":1},"end":{"line":20,"column":1}},"children":[{"type":"text","value":"1. Prerequisites","position":{"start":{"line":20,"column":1},"end":{"line":20,"column":1}},"key":"OFkG0CDpNG"}],"label":"env-prereqs","identifier":"env-prereqs","html_id":"env-prereqs","key":"c8c3SKyIcE"},{"type":"table","position":{"start":{"line":22,"column":1},"end":{"line":26,"column":1}},"children":[{"type":"tableRow","position":{"start":{"line":22,"column":1},"end":{"line":22,"column":1}},"children":[{"type":"tableCell","header":true,"position":{"start":{"line":22,"column":1},"end":{"line":22,"column":1}},"children":[{"type":"text","value":"Prerequisite","position":{"start":{"line":22,"column":1},"end":{"line":22,"column":1}},"key":"NZFhXsE9gd"}],"key":"OxiHb21AbU"},{"type":"tableCell","header":true,"position":{"start":{"line":22,"column":1},"end":{"line":22,"column":1}},"children":[{"type":"text","value":"Importance","position":{"start":{"line":22,"column":1},"end":{"line":22,"column":1}},"key":"zT2J5yiePS"}],"key":"Aquai4CYng"},{"type":"tableCell","header":true,"position":{"start":{"line":22,"column":1},"end":{"line":22,"column":1}},"children":[{"type":"text","value":"Notes","position":{"start":{"line":22,"column":1},"end":{"line":22,"column":1}},"key":"arZh3ktSuM"}],"key":"WED13cuxd1"}],"key":"I1QTLF2gUr"},{"type":"tableRow","position":{"start":{"line":24,"column":1},"end":{"line":24,"column":1}},"children":[{"type":"tableCell","position":{"start":{"line":24,"column":1},"end":{"line":24,"column":1}},"children":[{"type":"link","url":"https://pixi.sh/latest/installation/","position":{"start":{"line":24,"column":1},"end":{"line":24,"column":1}},"children":[{"type":"text","value":"Option 1: The Pixi package manager must be installed on the system running Jupyter Lab","position":{"start":{"line":24,"column":1},"end":{"line":24,"column":1}},"key":"P8vflzRzgm"}],"urlSource":"https://pixi.sh/latest/installation/","key":"g62FMvNUl8"}],"key":"O54kpcnP5u"},{"type":"tableCell","position":{"start":{"line":24,"column":1},"end":{"line":24,"column":1}},"children":[{"type":"text","value":"Necessary","position":{"start":{"line":24,"column":1},"end":{"line":24,"column":1}},"key":"hKWoy3Z8kA"}],"key":"Jcl0w8k6kP"},{"type":"tableCell","position":{"start":{"line":24,"column":1},"end":{"line":24,"column":1}},"children":[{"type":"text","value":"Pixi may not be supported on all Jupyter Hubs","position":{"start":{"line":24,"column":1},"end":{"line":24,"column":1}},"key":"Bgc2GICtsB"}],"key":"YAB7PL8kkC"}],"key":"zPrBd0XyZr"},{"type":"tableRow","position":{"start":{"line":25,"column":1},"end":{"line":25,"column":1}},"children":[{"type":"tableCell","position":{"start":{"line":25,"column":1},"end":{"line":25,"column":1}},"children":[{"type":"link","url":"https://www.docker.com/get-started/","position":{"start":{"line":25,"column":1},"end":{"line":25,"column":1}},"children":[{"type":"text","value":"Option 2: Docker must be installed and running on the system running Jupyter Lab","position":{"start":{"line":25,"column":1},"end":{"line":25,"column":1}},"key":"l6swaCcJoA"}],"urlSource":"https://www.docker.com/get-started/","key":"THPtJwm4Jl"}],"key":"zuCLc3DsIX"},{"type":"tableCell","position":{"start":{"line":25,"column":1},"end":{"line":25,"column":1}},"children":[{"type":"text","value":"Necessary","position":{"start":{"line":25,"column":1},"end":{"line":25,"column":1}},"key":"GqGDMVYzM0"}],"key":"SojLB919lJ"},{"type":"tableCell","position":{"start":{"line":25,"column":1},"end":{"line":25,"column":1}},"children":[{"type":"text","value":"Run the Docker image locally or in a Jupyter Hub","position":{"start":{"line":25,"column":1},"end":{"line":25,"column":1}},"key":"Hnn9TOSYgt"}],"key":"ncDQWEk8dt"}],"key":"g7XxF2Uwti"},{"type":"tableRow","position":{"start":{"line":26,"column":1},"end":{"line":26,"column":1}},"children":[{"type":"tableCell","position":{"start":{"line":26,"column":1},"end":{"line":26,"column":1}},"children":[{"type":"link","url":"https://rse-guidelines.readthedocs.io/en/latest/fundamentals/computing-development-environments/pixi/","position":{"start":{"line":26,"column":1},"end":{"line":26,"column":1}},"children":[{"type":"text","value":"UW Scientific Software Engineering Center’s Pixi guide","position":{"start":{"line":26,"column":1},"end":{"line":26,"column":1}},"key":"gpVR7zb2Dt"}],"urlSource":"https://rse-guidelines.readthedocs.io/en/latest/fundamentals/computing-development-environments/pixi/","key":"Dm2RhYF3TF"}],"key":"rXaGB48BzJ"},{"type":"tableCell","position":{"start":{"line":26,"column":1},"end":{"line":26,"column":1}},"children":[{"type":"text","value":"Helpful","position":{"start":{"line":26,"column":1},"end":{"line":26,"column":1}},"key":"TAy9mElA7Z"}],"key":"kAo7Q4pQ3H"},{"type":"tableCell","position":{"start":{"line":26,"column":1},"end":{"line":26,"column":1}},"children":[{"type":"text","value":"This is a great resource to get quickly get started with Pixi","position":{"start":{"line":26,"column":1},"end":{"line":26,"column":1}},"key":"zI82dIs223"}],"key":"FOKYVsLiJV"}],"key":"SvQjiCAxI7"}],"key":"YvFdOEhcr3"},{"type":"list","ordered":false,"spread":false,"position":{"start":{"line":28,"column":1},"end":{"line":29,"column":1}},"children":[{"type":"listItem","spread":true,"position":{"start":{"line":28,"column":1},"end":{"line":29,"column":1}},"children":[{"type":"paragraph","children":[{"type":"strong","position":{"start":{"line":28,"column":1},"end":{"line":28,"column":1}},"children":[{"type":"text","value":"Rough Notebook Time Estimate","position":{"start":{"line":28,"column":1},"end":{"line":28,"column":1}},"key":"lyQ7WShpuP"}],"key":"vkcr0PVa0C"},{"type":"text","value":": 3 minutes","position":{"start":{"line":28,"column":1},"end":{"line":28,"column":1}},"key":"mJnhGCOKnC"}],"key":"sh4W26G37j"}],"key":"JNqZTM11Ik"}],"key":"u9Gsj7cHy4"},{"type":"thematicBreak","key":"NzsqTO1IOd"},{"type":"heading","depth":2,"position":{"start":{"line":33,"column":1},"end":{"line":33,"column":1}},"children":[{"type":"text","value":"2. (Option 1) Install the environment with the Pixi pacakage manager","position":{"start":{"line":33,"column":1},"end":{"line":33,"column":1}},"key":"X63DXwqiKP"}],"label":"env-pixi","identifier":"env-pixi","html_id":"env-pixi","key":"sBtC7ddZoj"},{"type":"heading","depth":3,"position":{"start":{"line":35,"column":1},"end":{"line":35,"column":1}},"children":[{"type":"text","value":"2a. Create a ","position":{"start":{"line":35,"column":1},"end":{"line":35,"column":1}},"key":"Z0PXM3E0QJ"},{"type":"inlineCode","value":"work_dir","position":{"start":{"line":35,"column":1},"end":{"line":35,"column":1}},"key":"KjHWmsw1hZ"},{"type":"text","value":" context manager","position":{"start":{"line":35,"column":1},"end":{"line":35,"column":1}},"key":"OEfgSd3HPv"}],"identifier":"id-2a-create-a-work-dir-context-manager","label":"2a. Create a work_dir context manager","html_id":"id-2a-create-a-work-dir-context-manager","implicit":true,"key":"wBMoZTlL51"},{"type":"paragraph","position":{"start":{"line":37,"column":1},"end":{"line":37,"column":1}},"children":[{"type":"text","value":"This is useful when you want to run a command in a working directory and then automatically change back to your original directory","position":{"start":{"line":37,"column":1},"end":{"line":37,"column":1}},"key":"QM2L4v086k"}],"key":"o7re0EiE0W"}],"key":"twsNb8Nc9P"},{"type":"block","kind":"notebook-code","data":{"scrolled":true},"children":[{"type":"code","lang":"python","executable":true,"value":"import os\nfrom contextlib import contextmanager\nfrom pathlib import Path\n\n@contextmanager\ndef work_dir(new_dir):\n    old_dir = os.getcwd()\n    os.chdir(new_dir)\n    try:\n        yield\n    finally:\n        os.chdir(old_dir)","key":"xFDUozvH2T"},{"type":"outputs","id":"NHfBV3EBwF8RX7ojMozbl","children":[],"key":"FneMsmBEl2"}],"key":"az9mb4MBQF"},{"type":"block","kind":"notebook-content","children":[{"type":"heading","depth":3,"position":{"start":{"line":1,"column":1},"end":{"line":1,"column":1}},"children":[{"type":"text","value":"2b. Install the ","position":{"start":{"line":1,"column":1},"end":{"line":1,"column":1}},"key":"s0dKZvSSDs"},{"type":"inlineCode","value":"isce3","position":{"start":{"line":1,"column":1},"end":{"line":1,"column":1}},"key":"oA91x9gsXy"},{"type":"text","value":" environment with Pixi","position":{"start":{"line":1,"column":1},"end":{"line":1,"column":1}},"key":"QtOx7bEgGf"}],"identifier":"id-2b-install-the-isce3-environment-with-pixi","label":"2b. Install the isce3 environment with Pixi","html_id":"id-2b-install-the-isce3-environment-with-pixi","implicit":true,"key":"Zh3XLAWEe2"}],"key":"RBR4UtcSJs"},{"type":"block","kind":"notebook-code","data":{"scrolled":true},"children":[{"type":"code","lang":"python","executable":true,"value":"with work_dir(Path.cwd().parent):\n    !pixi install -e isce3","key":"QiCqtVMU9f"},{"type":"outputs","id":"yomn0ynLwXbmE8gOwGlNF","children":[],"key":"rIqIHNM4g7"}],"key":"zSiKFPMUFR"},{"type":"block","kind":"notebook-content","children":[{"type":"heading","depth":3,"position":{"start":{"line":1,"column":1},"end":{"line":1,"column":1}},"children":[{"type":"text","value":"2c. Register the ","position":{"start":{"line":1,"column":1},"end":{"line":1,"column":1}},"key":"Qc5V2C2kic"},{"type":"inlineCode","value":"isce3","position":{"start":{"line":1,"column":1},"end":{"line":1,"column":1}},"key":"jCZcoUp5Hh"},{"type":"text","value":" environment’s Python kernel with ","position":{"start":{"line":1,"column":1},"end":{"line":1,"column":1}},"key":"SpsMaJn3JQ"},{"type":"inlineCode","value":"ipykernel","position":{"start":{"line":1,"column":1},"end":{"line":1,"column":1}},"key":"CeAdS7Axvo"}],"identifier":"id-2c-register-the-isce3-environments-python-kernel-with-ipykernel","label":"2c. Register the isce3 environment’s Python kernel with ipykernel","html_id":"id-2c-register-the-isce3-environments-python-kernel-with-ipykernel","implicit":true,"key":"Y66SnIfRWH"}],"key":"zaLTH7RnVD"},{"type":"block","kind":"notebook-code","children":[{"type":"code","lang":"python","executable":true,"value":"env_name = \"isce3\"\ndisplay_name = f'\"{env_name} (Python)\"'\n\n!pixi run -e isce3 python -m ipykernel install \\\n  --user \\\n  --name $env_name \\\n  --display-name $display_name","key":"XZvksEde7d"},{"type":"outputs","id":"CM7BdntB76v-TvEwUU4x_","children":[],"key":"gPGLezt7u8"}],"key":"oOICAQZC7n"},{"type":"block","kind":"notebook-content","children":[{"type":"heading","depth":3,"position":{"start":{"line":1,"column":1},"end":{"line":1,"column":1}},"children":[{"type":"text","value":"2d. Ensure notebook shell commands run in the ","position":{"start":{"line":1,"column":1},"end":{"line":1,"column":1}},"key":"fgklTE5Zfb"},{"type":"inlineCode","value":"isce3","position":{"start":{"line":1,"column":1},"end":{"line":1,"column":1}},"key":"tjd9VrkrSJ"},{"type":"text","value":" environment","position":{"start":{"line":1,"column":1},"end":{"line":1,"column":1}},"key":"aZX0vGWHWm"}],"identifier":"id-2d-ensure-notebook-shell-commands-run-in-the-isce3-environment","label":"2d. Ensure notebook shell commands run in the isce3 environment","html_id":"id-2d-ensure-notebook-shell-commands-run-in-the-isce3-environment","implicit":true,"key":"HRhIV7aJzt"},{"type":"paragraph","position":{"start":{"line":3,"column":1},"end":{"line":3,"column":1}},"children":[{"type":"text","value":"This ensures that shell commands executed from inside a notebook with ","position":{"start":{"line":3,"column":1},"end":{"line":3,"column":1}},"key":"Sv5NRrUq9g"},{"type":"inlineCode","value":"!","position":{"start":{"line":3,"column":1},"end":{"line":3,"column":1}},"key":"VKNLBavvXu"},{"type":"text","value":" run in the notebook kernel’s environment. This works by launching the entire Jupyter kernel process inside the Pixi environment, so the kernel’s PATH, environment variables, and Python executable all come from that Pixi environment, not from the parent JupyterLab environment.","position":{"start":{"line":3,"column":1},"end":{"line":3,"column":1}},"key":"OEdUMQrn7t"}],"key":"iTNLP7khj0"}],"key":"W7owxsaTKf"},{"type":"block","kind":"notebook-code","children":[{"type":"code","lang":"python","executable":true,"value":"from jupyter_client.kernelspec import KernelSpecManager\nimport json\n\nksm = KernelSpecManager()\nspec = ksm.get_kernel_spec(env_name)\nkernel_dir = Path(spec.resource_dir)\nkernel_json = kernel_dir / \"kernel.json\"\n\ndata = json.loads(kernel_json.read_text())\norig_argv = data.get(\"argv\", [])\n\nnew_argv = [\n    \"pixi\",\n    \"run\",\n    \"--manifest-path\",\n    str(Path.cwd().parent),\n    \"-e\",\n    env_name,\n] + orig_argv\n\ndata[\"argv\"] = new_argv\nkernel_json.write_text(json.dumps(data, indent=2))\nprint(f\"Updated kernel.json at {kernel_json} with Pixi wrapper.\")\nprint(\"argv:\", data[\"argv\"])","key":"JZfUNSo09u"},{"type":"outputs","id":"FX-BEG3l-MsTPBVp3GTeD","children":[],"key":"iNaDoLrMBz"}],"key":"THmYlaNmu4"},{"type":"block","kind":"notebook-content","children":[{"type":"heading","depth":3,"position":{"start":{"line":1,"column":1},"end":{"line":1,"column":1}},"children":[{"type":"text","value":"2e. (Optional) Delete the environment and remove its ","position":{"start":{"line":1,"column":1},"end":{"line":1,"column":1}},"key":"hdWu9994m3"},{"type":"inlineCode","value":"kernelspec","position":{"start":{"line":1,"column":1},"end":{"line":1,"column":1}},"key":"uwUZjpqtF8"}],"identifier":"id-2e-optional-delete-the-environment-and-remove-its-kernelspec","label":"2e. (Optional) Delete the environment and remove its kernelspec","html_id":"id-2e-optional-delete-the-environment-and-remove-its-kernelspec","implicit":true,"key":"dEvA32SJtD"}],"key":"Altpyvwkde"},{"type":"block","kind":"notebook-code","children":[{"type":"code","lang":"python","executable":true,"value":"with work_dir(Path.cwd().parent):\n    !pixi clean\n    !jupyter kernelspec remove isce3 -y","key":"xwwdCChsIf"},{"type":"outputs","id":"Oq2e9C1Zrr3QE9MLMLnMn","children":[],"key":"wyvATjAgGj"}],"key":"nlXqcG48Yl"},{"type":"block","kind":"notebook-content","children":[{"type":"thematicBreak","key":"KCmBm5PEmX"}],"key":"im3Vb2aWt9"},{"type":"block","kind":"notebook-content","children":[{"type":"heading","depth":2,"position":{"start":{"line":2,"column":1},"end":{"line":2,"column":1}},"children":[{"type":"text","value":"3. (Option 2) Run a Docker Image with the software environment already installed","position":{"start":{"line":2,"column":1},"end":{"line":2,"column":1}},"key":"PiwOQa2CZs"}],"label":"env-docker","identifier":"env-docker","html_id":"env-docker","key":"wapuAFInT0"},{"type":"paragraph","position":{"start":{"line":4,"column":1},"end":{"line":4,"column":1}},"children":[{"type":"text","value":"Coming soon","position":{"start":{"line":4,"column":1},"end":{"line":4,"column":1}},"key":"cvmK4YWq3l"}],"key":"mPbR35kPlf"}],"key":"XdRZmSWckJ"},{"type":"block","kind":"notebook-content","children":[{"type":"heading","depth":2,"position":{"start":{"line":2,"column":1},"end":{"line":2,"column":1}},"children":[{"type":"text","value":"4. Summary","position":{"start":{"line":2,"column":1},"end":{"line":2,"column":1}},"key":"C1VXOKvP7s"}],"label":"env-summary","identifier":"env-summary","html_id":"env-summary","key":"srR5L9blFf"},{"type":"paragraph","position":{"start":{"line":3,"column":1},"end":{"line":3,"column":1}},"children":[{"type":"text","value":"Now that you have installed the software environment or have the Docker image running, ","position":{"start":{"line":3,"column":1},"end":{"line":3,"column":1}},"key":"luwtr0WELv"},{"type":"link","url":"https://github.com/ASFOpenSARlab/NISAR_GCOV_Cookbook/blob/main/notebooks/set_up_Earthdata_Login.md","position":{"start":{"line":3,"column":1},"end":{"line":3,"column":1}},"children":[{"type":"text","value":"make sure you have access to the data","position":{"start":{"line":3,"column":1},"end":{"line":3,"column":1}},"key":"kq0lCxDwuI"}],"urlSource":"https://github.com/ASFOpenSARlab/NISAR_GCOV_Cookbook/blob/main/notebooks/set_up_Earthdata_Login.md","data":{"kind":"file","org":"ASFOpenSARlab","repo":"NISAR_GCOV_Cookbook","reference":"main","file":"notebooks/set_up_Earthdata_Login.md","raw":"https://raw.githubusercontent.com/ASFOpenSARlab/NISAR_GCOV_Cookbook/main/notebooks/set_up_Earthdata_Login.md"},"internal":false,"protocol":"github","key":"Y0iSmpTZGz"},{"type":"text","value":". You will then be ready to run the remaining notebooks in the NISAR GCOV Cookbook.","position":{"start":{"line":3,"column":1},"end":{"line":3,"column":1}},"key":"mmu80KcG3S"}],"key":"MeKDA2V2bL"},{"type":"thematicBreak","key":"AnE0AjADXx"}],"key":"NwByK0Viml"},{"type":"block","kind":"notebook-content","children":[{"type":"heading","depth":2,"position":{"start":{"line":2,"column":1},"end":{"line":2,"column":1}},"children":[{"type":"text","value":"5. Resources and references","position":{"start":{"line":2,"column":1},"end":{"line":2,"column":1}},"key":"XDMzVahpza"}],"label":"env-resources","identifier":"env-resources","html_id":"env-resources","key":"mtLxHSMQJX"},{"type":"heading","depth":3,"position":{"start":{"line":4,"column":1},"end":{"line":4,"column":1}},"children":[{"type":"text","value":"References","position":{"start":{"line":4,"column":1},"end":{"line":4,"column":1}},"key":"GgZTCwWSVK"}],"identifier":"references","label":"References","html_id":"references","implicit":true,"key":"ncoUbUQnQc"},{"type":"list","ordered":false,"spread":false,"position":{"start":{"line":5,"column":1},"end":{"line":6,"column":1}},"children":[{"type":"listItem","spread":true,"position":{"start":{"line":5,"column":1},"end":{"line":6,"column":1}},"children":[{"type":"paragraph","children":[{"type":"link","url":"https://escience.washington.edu/software-engineering/ssec/","position":{"start":{"line":5,"column":1},"end":{"line":5,"column":1}},"children":[{"type":"abbreviation","title":"Univertsity of Washington Scientific Software Engineering Center","children":[{"type":"text","value":"UW SSEC","key":"IOGewaAupu"}],"key":"ouTwy883oq"}],"urlSource":"https://escience.washington.edu/software-engineering/ssec/","key":"SWg7dyjlCA"}],"key":"azDPPFjLPL"}],"key":"RBtVtNptpR"}],"key":"y4KJL92yjs"},{"type":"paragraph","position":{"start":{"line":7,"column":1},"end":{"line":7,"column":1}},"children":[{"type":"strong","position":{"start":{"line":7,"column":1},"end":{"line":7,"column":1}},"children":[{"type":"text","value":"Author:","position":{"start":{"line":7,"column":1},"end":{"line":7,"column":1}},"key":"fnMpU6wyXm"}],"key":"gttYhqWIu4"},{"type":"text","value":" Alex Lewandowski","position":{"start":{"line":7,"column":1},"end":{"line":7,"column":1}},"key":"UF6ReuEqCR"}],"key":"AqVBtwAqof"}],"key":"fbFDMhICuq"}],"key":"dJVVOqbMhI"},"references":{"cite":{"order":[],"data":{}}},"footer":{"navigation":{"prev":{"title":"Understanding HDF5 Files","url":"/notebooks/hdf5-intro","group":"NISAR GCOV Product Specification"},"next":{"title":"Set Up an Earthdata Login Account for NISAR Data Access","url":"/notebooks/set-up-earthdata-login","group":"Cookbook Set Up"}}},"domain":"http://localhost:3000"}